[[{"from":0,"to":76,"value":0.1961206897,"title":"P(B|A): 19.61%","fnode":"Contusion","tnode":"Thrombocytopenia"},{"from":0,"to":86,"value":0.2219827586,"title":"P(B|A): 22.2%","fnode":"Contusion","tnode":"Pain"},{"from":0,"to":89,"value":0.1400862069,"title":"P(B|A): 14.01%","fnode":"Contusion","tnode":"Pain in extremity"},{"from":0,"to":90,"value":0.1594827586,"title":"P(B|A): 15.95%","fnode":"Contusion","tnode":"Arthralgia"},{"from":0,"to":96,"value":0.1379310345,"title":"P(B|A): 13.79%","fnode":"Contusion","tnode":"Nausea"},{"from":0,"to":97,"value":0.2112068966,"title":"P(B|A): 21.12%","fnode":"Contusion","tnode":"Fatigue"},{"from":0,"to":98,"value":0.1659482759,"title":"P(B|A): 16.59%","fnode":"Contusion","tnode":"Pyrexia"},{"from":0,"to":99,"value":0.3620689655,"title":"P(B|A): 36.21%","fnode":"Contusion","tnode":"Headache"},{"from":1,"to":15,"value":0.1532033426,"title":"P(B|A): 15.32%","fnode":"Hemiparesis","tnode":"Aphasia"},{"from":1,"to":76,"value":0.1504178273,"title":"P(B|A): 15.04%","fnode":"Hemiparesis","tnode":"Thrombocytopenia"},{"from":1,"to":82,"value":0.1504178273,"title":"P(B|A): 15.04%","fnode":"Hemiparesis","tnode":"Death"},{"from":1,"to":83,"value":0.2534818942,"title":"P(B|A): 25.35%","fnode":"Hemiparesis","tnode":"Cerebrovascular accident"},{"from":1,"to":99,"value":0.2924791086,"title":"P(B|A): 29.25%","fnode":"Hemiparesis","tnode":"Headache"},{"from":2,"to":82,"value":0.3482849604,"title":"P(B|A): 34.83%","fnode":"Acute myocardial infarction","tnode":"Death"},{"from":2,"to":84,"value":0.1715039578,"title":"P(B|A): 17.15%","fnode":"Acute myocardial infarction","tnode":"Chest pain"},{"from":2,"to":95,"value":0.1292875989,"title":"P(B|A): 12.93%","fnode":"Acute myocardial infarction","tnode":"Dyspnoea"},{"from":3,"to":86,"value":0.1351981352,"title":"P(B|A): 13.52%","fnode":"Epistaxis","tnode":"Pain"},{"from":3,"to":97,"value":0.2097902098,"title":"P(B|A): 20.98%","fnode":"Epistaxis","tnode":"Fatigue"},{"from":3,"to":98,"value":0.1841491841,"title":"P(B|A): 18.41%","fnode":"Epistaxis","tnode":"Pyrexia"},{"from":3,"to":99,"value":0.2983682984,"title":"P(B|A): 29.84%","fnode":"Epistaxis","tnode":"Headache"},{"from":4,"to":82,"value":1.0,"title":"P(B|A): 100.0%","fnode":"Sudden death","tnode":"Death"},{"from":5,"to":79,"value":0.1301939058,"title":"P(B|A): 13.02%","fnode":"Dysphagia","tnode":"Hypoaesthesia"},{"from":5,"to":82,"value":0.2022160665,"title":"P(B|A): 20.22%","fnode":"Dysphagia","tnode":"Death"},{"from":5,"to":86,"value":0.1440443213,"title":"P(B|A): 14.4%","fnode":"Dysphagia","tnode":"Pain"},{"from":5,"to":95,"value":0.2188365651,"title":"P(B|A): 21.88%","fnode":"Dysphagia","tnode":"Dyspnoea"},{"from":5,"to":97,"value":0.1606648199,"title":"P(B|A): 16.07%","fnode":"Dysphagia","tnode":"Fatigue"},{"from":5,"to":98,"value":0.1329639889,"title":"P(B|A): 13.3%","fnode":"Dysphagia","tnode":"Pyrexia"},{"from":5,"to":99,"value":0.163434903,"title":"P(B|A): 16.34%","fnode":"Dysphagia","tnode":"Headache"},{"from":6,"to":82,"value":0.1344339623,"title":"P(B|A): 13.44%","fnode":"Cerebral infarction","tnode":"Death"},{"from":6,"to":99,"value":0.1438679245,"title":"P(B|A): 14.39%","fnode":"Cerebral infarction","tnode":"Headache"},{"from":7,"to":82,"value":0.4532110092,"title":"P(B|A): 45.32%","fnode":"Cardiac failure","tnode":"Death"},{"from":7,"to":95,"value":0.2311926606,"title":"P(B|A): 23.12%","fnode":"Cardiac failure","tnode":"Dyspnoea"},{"from":8,"to":67,"value":0.1550218341,"title":"P(B|A): 15.5%","fnode":"Feeling cold","tnode":"Tremor"},{"from":8,"to":86,"value":0.3777292576,"title":"P(B|A): 37.77%","fnode":"Feeling cold","tnode":"Pain"},{"from":8,"to":87,"value":0.1768558952,"title":"P(B|A): 17.69%","fnode":"Feeling cold","tnode":"Asthenia"},{"from":8,"to":89,"value":0.1986899563,"title":"P(B|A): 19.87%","fnode":"Feeling cold","tnode":"Pain in extremity"},{"from":8,"to":90,"value":0.1834061135,"title":"P(B|A): 18.34%","fnode":"Feeling cold","tnode":"Arthralgia"},{"from":8,"to":91,"value":0.1593886463,"title":"P(B|A): 15.94%","fnode":"Feeling cold","tnode":"Malaise"},{"from":8,"to":92,"value":0.2183406114,"title":"P(B|A): 21.83%","fnode":"Feeling cold","tnode":"Dizziness"},{"from":8,"to":93,"value":0.2336244541,"title":"P(B|A): 23.36%","fnode":"Feeling cold","tnode":"Myalgia"},{"from":8,"to":94,"value":0.4148471616,"title":"P(B|A): 41.48%","fnode":"Feeling cold","tnode":"Chills"},{"from":8,"to":95,"value":0.1331877729,"title":"P(B|A): 13.32%","fnode":"Feeling cold","tnode":"Dyspnoea"},{"from":8,"to":96,"value":0.211790393,"title":"P(B|A): 21.18%","fnode":"Feeling cold","tnode":"Nausea"},{"from":8,"to":97,"value":0.4279475983,"title":"P(B|A): 42.79%","fnode":"Feeling cold","tnode":"Fatigue"},{"from":8,"to":98,"value":0.3777292576,"title":"P(B|A): 37.77%","fnode":"Feeling cold","tnode":"Pyrexia"},{"from":8,"to":99,"value":0.4672489083,"title":"P(B|A): 46.72%","fnode":"Feeling cold","tnode":"Headache"},{"from":9,"to":37,"value":0.1346578366,"title":"P(B|A): 13.47%","fnode":"Musculoskeletal stiffness","tnode":"Neck pain"},{"from":9,"to":86,"value":0.3311258278,"title":"P(B|A): 33.11%","fnode":"Musculoskeletal stiffness","tnode":"Pain"},{"from":9,"to":89,"value":0.233995585,"title":"P(B|A): 23.4%","fnode":"Musculoskeletal stiffness","tnode":"Pain in extremity"},{"from":9,"to":90,"value":0.2671081678,"title":"P(B|A): 26.71%","fnode":"Musculoskeletal stiffness","tnode":"Arthralgia"},{"from":9,"to":91,"value":0.1214128035,"title":"P(B|A): 12.14%","fnode":"Musculoskeletal stiffness","tnode":"Malaise"},{"from":9,"to":92,"value":0.1721854305,"title":"P(B|A): 17.22%","fnode":"Musculoskeletal stiffness","tnode":"Dizziness"},{"from":9,"to":93,"value":0.2273730684,"title":"P(B|A): 22.74%","fnode":"Musculoskeletal stiffness","tnode":"Myalgia"},{"from":9,"to":94,"value":0.2052980132,"title":"P(B|A): 20.53%","fnode":"Musculoskeletal stiffness","tnode":"Chills"},{"from":9,"to":96,"value":0.229580574,"title":"P(B|A): 22.96%","fnode":"Musculoskeletal stiffness","tnode":"Nausea"},{"from":9,"to":97,"value":0.3509933775,"title":"P(B|A): 35.1%","fnode":"Musculoskeletal stiffness","tnode":"Fatigue"},{"from":9,"to":98,"value":0.2803532009,"title":"P(B|A): 28.04%","fnode":"Musculoskeletal stiffness","tnode":"Pyrexia"},{"from":9,"to":99,"value":0.4900662252,"title":"P(B|A): 49.01%","fnode":"Musculoskeletal stiffness","tnode":"Headache"},{"from":10,"to":26,"value":0.1791304348,"title":"P(B|A): 17.91%","fnode":"Cerebral venous sinus thrombosis","tnode":"Cerebral haemorrhage"},{"from":10,"to":76,"value":0.4608695652,"title":"P(B|A): 46.09%","fnode":"Cerebral venous sinus thrombosis","tnode":"Thrombocytopenia"},{"from":10,"to":82,"value":0.1860869565,"title":"P(B|A): 18.61%","fnode":"Cerebral venous sinus thrombosis","tnode":"Death"},{"from":10,"to":88,"value":0.1339130435,"title":"P(B|A): 13.39%","fnode":"Cerebral venous sinus thrombosis","tnode":"Vomiting"},{"from":10,"to":99,"value":0.5530434783,"title":"P(B|A): 55.3%","fnode":"Cerebral venous sinus thrombosis","tnode":"Headache"},{"from":11,"to":82,"value":0.6132596685,"title":"P(B|A): 61.33%","fnode":"Unresponsive to stimuli","tnode":"Death"},{"from":11,"to":88,"value":0.1243093923,"title":"P(B|A): 12.43%","fnode":"Unresponsive to stimuli","tnode":"Vomiting"},{"from":11,"to":95,"value":0.1546961326,"title":"P(B|A): 15.47%","fnode":"Unresponsive to stimuli","tnode":"Dyspnoea"},{"from":11,"to":98,"value":0.1546961326,"title":"P(B|A): 15.47%","fnode":"Unresponsive to stimuli","tnode":"Pyrexia"},{"from":12,"to":19,"value":0.1444954128,"title":"P(B|A): 14.45%","fnode":"Dysarthria","tnode":"Facial paralysis"},{"from":12,"to":60,"value":0.121559633,"title":"P(B|A): 12.16%","fnode":"Dysarthria","tnode":"Muscular weakness"},{"from":12,"to":64,"value":0.1444954128,"title":"P(B|A): 14.45%","fnode":"Dysarthria","tnode":"Confusional state"},{"from":12,"to":79,"value":0.130733945,"title":"P(B|A): 13.07%","fnode":"Dysarthria","tnode":"Hypoaesthesia"},{"from":12,"to":83,"value":0.2339449541,"title":"P(B|A): 23.39%","fnode":"Dysarthria","tnode":"Cerebrovascular accident"},{"from":12,"to":87,"value":0.1559633028,"title":"P(B|A): 15.6%","fnode":"Dysarthria","tnode":"Asthenia"},{"from":12,"to":92,"value":0.1330275229,"title":"P(B|A): 13.3%","fnode":"Dysarthria","tnode":"Dizziness"},{"from":12,"to":97,"value":0.1559633028,"title":"P(B|A): 15.6%","fnode":"Dysarthria","tnode":"Fatigue"},{"from":12,"to":99,"value":0.2133027523,"title":"P(B|A): 21.33%","fnode":"Dysarthria","tnode":"Headache"},{"from":13,"to":86,"value":0.1270833333,"title":"P(B|A): 12.71%","fnode":"Visual impairment","tnode":"Pain"},{"from":13,"to":92,"value":0.225,"title":"P(B|A): 22.5%","fnode":"Visual impairment","tnode":"Dizziness"},{"from":13,"to":96,"value":0.1875,"title":"P(B|A): 18.75%","fnode":"Visual impairment","tnode":"Nausea"},{"from":13,"to":97,"value":0.2,"title":"P(B|A): 20.0%","fnode":"Visual impairment","tnode":"Fatigue"},{"from":13,"to":98,"value":0.13125,"title":"P(B|A): 13.12%","fnode":"Visual impairment","tnode":"Pyrexia"},{"from":13,"to":99,"value":0.45,"title":"P(B|A): 45.0%","fnode":"Visual impairment","tnode":"Headache"},{"from":14,"to":45,"value":0.156462585,"title":"P(B|A): 15.65%","fnode":"Feeling hot","tnode":"Erythema"},{"from":14,"to":59,"value":0.1315192744,"title":"P(B|A): 13.15%","fnode":"Feeling hot","tnode":"Hyperhidrosis"},{"from":14,"to":80,"value":0.1496598639,"title":"P(B|A): 14.97%","fnode":"Feeling hot","tnode":"Paraesthesia"},{"from":14,"to":86,"value":0.2517006803,"title":"P(B|A): 25.17%","fnode":"Feeling hot","tnode":"Pain"},{"from":14,"to":89,"value":0.1541950113,"title":"P(B|A): 15.42%","fnode":"Feeling hot","tnode":"Pain in extremity"},{"from":14,"to":90,"value":0.1541950113,"title":"P(B|A): 15.42%","fnode":"Feeling hot","tnode":"Arthralgia"},{"from":14,"to":91,"value":0.1678004535,"title":"P(B|A): 16.78%","fnode":"Feeling hot","tnode":"Malaise"},{"from":14,"to":92,"value":0.2675736961,"title":"P(B|A): 26.76%","fnode":"Feeling hot","tnode":"Dizziness"},{"from":14,"to":93,"value":0.1541950113,"title":"P(B|A): 15.42%","fnode":"Feeling hot","tnode":"Myalgia"},{"from":14,"to":94,"value":0.2403628118,"title":"P(B|A): 24.04%","fnode":"Feeling hot","tnode":"Chills"},{"from":14,"to":95,"value":0.2244897959,"title":"P(B|A): 22.45%","fnode":"Feeling hot","tnode":"Dyspnoea"},{"from":14,"to":96,"value":0.2222222222,"title":"P(B|A): 22.22%","fnode":"Feeling hot","tnode":"Nausea"},{"from":14,"to":97,"value":0.3083900227,"title":"P(B|A): 30.84%","fnode":"Feeling hot","tnode":"Fatigue"},{"from":14,"to":98,"value":0.2585034014,"title":"P(B|A): 25.85%","fnode":"Feeling hot","tnode":"Pyrexia"},{"from":14,"to":99,"value":0.3628117914,"title":"P(B|A): 36.28%","fnode":"Feeling hot","tnode":"Headache"},{"from":15,"to":1,"value":0.125284738,"title":"P(B|A): 12.53%","fnode":"Aphasia","tnode":"Hemiparesis"},{"from":15,"to":82,"value":0.1343963554,"title":"P(B|A): 13.44%","fnode":"Aphasia","tnode":"Death"},{"from":15,"to":83,"value":0.2050113895,"title":"P(B|A): 20.5%","fnode":"Aphasia","tnode":"Cerebrovascular accident"},{"from":15,"to":99,"value":0.2050113895,"title":"P(B|A): 20.5%","fnode":"Aphasia","tnode":"Headache"},{"from":16,"to":47,"value":0.124726477,"title":"P(B|A): 12.47%","fnode":"Balance disorder","tnode":"Vertigo"},{"from":16,"to":86,"value":0.1203501094,"title":"P(B|A): 12.04%","fnode":"Balance disorder","tnode":"Pain"},{"from":16,"to":87,"value":0.1641137856,"title":"P(B|A): 16.41%","fnode":"Balance disorder","tnode":"Asthenia"},{"from":16,"to":92,"value":0.409190372,"title":"P(B|A): 40.92%","fnode":"Balance disorder","tnode":"Dizziness"},{"from":16,"to":96,"value":0.249452954,"title":"P(B|A): 24.95%","fnode":"Balance disorder","tnode":"Nausea"},{"from":16,"to":97,"value":0.284463895,"title":"P(B|A): 28.45%","fnode":"Balance disorder","tnode":"Fatigue"},{"from":16,"to":98,"value":0.1531728665,"title":"P(B|A): 15.32%","fnode":"Balance disorder","tnode":"Pyrexia"},{"from":16,"to":99,"value":0.3457330416,"title":"P(B|A): 34.57%","fnode":"Balance disorder","tnode":"Headache"},{"from":17,"to":60,"value":0.1731092437,"title":"P(B|A): 17.31%","fnode":"Guillain-Barre syndrome","tnode":"Muscular weakness"},{"from":17,"to":79,"value":0.1327731092,"title":"P(B|A): 13.28%","fnode":"Guillain-Barre syndrome","tnode":"Hypoaesthesia"},{"from":17,"to":80,"value":0.1831932773,"title":"P(B|A): 18.32%","fnode":"Guillain-Barre syndrome","tnode":"Paraesthesia"},{"from":18,"to":86,"value":0.2226345083,"title":"P(B|A): 22.26%","fnode":"Injection site pain","tnode":"Pain"},{"from":18,"to":89,"value":0.1243042672,"title":"P(B|A): 12.43%","fnode":"Injection site pain","tnode":"Pain in extremity"},{"from":18,"to":90,"value":0.2133580705,"title":"P(B|A): 21.34%","fnode":"Injection site pain","tnode":"Arthralgia"},{"from":18,"to":91,"value":0.1836734694,"title":"P(B|A): 18.37%","fnode":"Injection site pain","tnode":"Malaise"},{"from":18,"to":92,"value":0.1985157699,"title":"P(B|A): 19.85%","fnode":"Injection site pain","tnode":"Dizziness"},{"from":18,"to":93,"value":0.3246753247,"title":"P(B|A): 32.47%","fnode":"Injection site pain","tnode":"Myalgia"},{"from":18,"to":94,"value":0.3209647495,"title":"P(B|A): 32.1%","fnode":"Injection site pain","tnode":"Chills"},{"from":18,"to":96,"value":0.3079777365,"title":"P(B|A): 30.8%","fnode":"Injection site pain","tnode":"Nausea"},{"from":18,"to":97,"value":0.4452690167,"title":"P(B|A): 44.53%","fnode":"Injection site pain","tnode":"Fatigue"},{"from":18,"to":98,"value":0.4378478664,"title":"P(B|A): 43.78%","fnode":"Injection site pain","tnode":"Pyrexia"},{"from":18,"to":99,"value":0.5361781076,"title":"P(B|A): 53.62%","fnode":"Injection site pain","tnode":"Headache"},{"from":19,"to":12,"value":0.1340425532,"title":"P(B|A): 13.4%","fnode":"Facial paralysis","tnode":"Dysarthria"},{"from":19,"to":79,"value":0.1425531915,"title":"P(B|A): 14.26%","fnode":"Facial paralysis","tnode":"Hypoaesthesia"},{"from":19,"to":99,"value":0.1553191489,"title":"P(B|A): 15.53%","fnode":"Facial paralysis","tnode":"Headache"},{"from":20,"to":77,"value":0.1285046729,"title":"P(B|A): 12.85%","fnode":"Oxygen saturation decreased","tnode":"Cough"},{"from":20,"to":78,"value":0.1261682243,"title":"P(B|A): 12.62%","fnode":"Oxygen saturation decreased","tnode":"COVID-19"},{"from":20,"to":82,"value":0.3154205607,"title":"P(B|A): 31.54%","fnode":"Oxygen saturation decreased","tnode":"Death"},{"from":20,"to":87,"value":0.1285046729,"title":"P(B|A): 12.85%","fnode":"Oxygen saturation decreased","tnode":"Asthenia"},{"from":20,"to":95,"value":0.4135514019,"title":"P(B|A): 41.36%","fnode":"Oxygen saturation decreased","tnode":"Dyspnoea"},{"from":20,"to":97,"value":0.1518691589,"title":"P(B|A): 15.19%","fnode":"Oxygen saturation decreased","tnode":"Fatigue"},{"from":20,"to":98,"value":0.308411215,"title":"P(B|A): 30.84%","fnode":"Oxygen saturation decreased","tnode":"Pyrexia"},{"from":20,"to":99,"value":0.1518691589,"title":"P(B|A): 15.19%","fnode":"Oxygen saturation decreased","tnode":"Headache"},{"from":21,"to":50,"value":0.1238273921,"title":"P(B|A): 12.38%","fnode":"Illness","tnode":"Migraine"},{"from":21,"to":81,"value":0.1575984991,"title":"P(B|A): 15.76%","fnode":"Illness","tnode":"Diarrhoea"},{"from":21,"to":86,"value":0.2138836773,"title":"P(B|A): 21.39%","fnode":"Illness","tnode":"Pain"},{"from":21,"to":88,"value":0.1407129456,"title":"P(B|A): 14.07%","fnode":"Illness","tnode":"Vomiting"},{"from":21,"to":91,"value":0.1332082552,"title":"P(B|A): 13.32%","fnode":"Illness","tnode":"Malaise"},{"from":21,"to":92,"value":0.2101313321,"title":"P(B|A): 21.01%","fnode":"Illness","tnode":"Dizziness"},{"from":21,"to":94,"value":0.181988743,"title":"P(B|A): 18.2%","fnode":"Illness","tnode":"Chills"},{"from":21,"to":96,"value":0.1707317073,"title":"P(B|A): 17.07%","fnode":"Illness","tnode":"Nausea"},{"from":21,"to":97,"value":0.2626641651,"title":"P(B|A): 26.27%","fnode":"Illness","tnode":"Fatigue"},{"from":21,"to":98,"value":0.2889305816,"title":"P(B|A): 28.89%","fnode":"Illness","tnode":"Pyrexia"},{"from":21,"to":99,"value":0.4746716698,"title":"P(B|A): 47.47%","fnode":"Illness","tnode":"Headache"},{"from":22,"to":82,"value":0.5841121495,"title":"P(B|A): 58.41%","fnode":"General physical health deterioration","tnode":"Death"},{"from":22,"to":95,"value":0.1822429907,"title":"P(B|A): 18.22%","fnode":"General physical health deterioration","tnode":"Dyspnoea"},{"from":22,"to":97,"value":0.1612149533,"title":"P(B|A): 16.12%","fnode":"General physical health deterioration","tnode":"Fatigue"},{"from":22,"to":98,"value":0.2406542056,"title":"P(B|A): 24.07%","fnode":"General physical health deterioration","tnode":"Pyrexia"},{"from":23,"to":78,"value":0.8867521368,"title":"P(B|A): 88.68%","fnode":"Drug ineffective","tnode":"COVID-19"},{"from":23,"to":82,"value":0.311965812,"title":"P(B|A): 31.2%","fnode":"Drug ineffective","tnode":"Death"},{"from":24,"to":82,"value":0.1242829828,"title":"P(B|A): 12.43%","fnode":"Lethargy","tnode":"Death"},{"from":24,"to":86,"value":0.2026768642,"title":"P(B|A): 20.27%","fnode":"Lethargy","tnode":"Pain"},{"from":24,"to":87,"value":0.1319311663,"title":"P(B|A): 13.19%","fnode":"Lethargy","tnode":"Asthenia"},{"from":24,"to":89,"value":0.1223709369,"title":"P(B|A): 12.24%","fnode":"Lethargy","tnode":"Pain in extremity"},{"from":24,"to":90,"value":0.1625239006,"title":"P(B|A): 16.25%","fnode":"Lethargy","tnode":"Arthralgia"},{"from":24,"to":91,"value":0.1281070746,"title":"P(B|A): 12.81%","fnode":"Lethargy","tnode":"Malaise"},{"from":24,"to":92,"value":0.1950286807,"title":"P(B|A): 19.5%","fnode":"Lethargy","tnode":"Dizziness"},{"from":24,"to":93,"value":0.1338432122,"title":"P(B|A): 13.38%","fnode":"Lethargy","tnode":"Myalgia"},{"from":24,"to":94,"value":0.189292543,"title":"P(B|A): 18.93%","fnode":"Lethargy","tnode":"Chills"},{"from":24,"to":95,"value":0.1778202677,"title":"P(B|A): 17.78%","fnode":"Lethargy","tnode":"Dyspnoea"},{"from":24,"to":96,"value":0.2217973231,"title":"P(B|A): 22.18%","fnode":"Lethargy","tnode":"Nausea"},{"from":24,"to":97,"value":0.2791586998,"title":"P(B|A): 27.92%","fnode":"Lethargy","tnode":"Fatigue"},{"from":24,"to":98,"value":0.3059273423,"title":"P(B|A): 30.59%","fnode":"Lethargy","tnode":"Pyrexia"},{"from":24,"to":99,"value":0.3747609943,"title":"P(B|A): 37.48%","fnode":"Lethargy","tnode":"Headache"},{"from":25,"to":79,"value":0.1220825853,"title":"P(B|A): 12.21%","fnode":"Muscle spasms","tnode":"Hypoaesthesia"},{"from":25,"to":80,"value":0.1364452424,"title":"P(B|A): 13.64%","fnode":"Muscle spasms","tnode":"Paraesthesia"},{"from":25,"to":86,"value":0.3393177738,"title":"P(B|A): 33.93%","fnode":"Muscle spasms","tnode":"Pain"},{"from":25,"to":89,"value":0.2064631957,"title":"P(B|A): 20.65%","fnode":"Muscle spasms","tnode":"Pain in extremity"},{"from":25,"to":90,"value":0.1867145422,"title":"P(B|A): 18.67%","fnode":"Muscle spasms","tnode":"Arthralgia"},{"from":25,"to":92,"value":0.2190305206,"title":"P(B|A): 21.9%","fnode":"Muscle spasms","tnode":"Dizziness"},{"from":25,"to":93,"value":0.2657091562,"title":"P(B|A): 26.57%","fnode":"Muscle spasms","tnode":"Myalgia"},{"from":25,"to":94,"value":0.2136445242,"title":"P(B|A): 21.36%","fnode":"Muscle spasms","tnode":"Chills"},{"from":25,"to":95,"value":0.1543985637,"title":"P(B|A): 15.44%","fnode":"Muscle spasms","tnode":"Dyspnoea"},{"from":25,"to":96,"value":0.2082585278,"title":"P(B|A): 20.83%","fnode":"Muscle spasms","tnode":"Nausea"},{"from":25,"to":97,"value":0.2908438061,"title":"P(B|A): 29.08%","fnode":"Muscle spasms","tnode":"Fatigue"},{"from":25,"to":98,"value":0.2603231598,"title":"P(B|A): 26.03%","fnode":"Muscle spasms","tnode":"Pyrexia"},{"from":25,"to":99,"value":0.3195691203,"title":"P(B|A): 31.96%","fnode":"Muscle spasms","tnode":"Headache"},{"from":26,"to":10,"value":0.1708126036,"title":"P(B|A): 17.08%","fnode":"Cerebral haemorrhage","tnode":"Cerebral venous sinus thrombosis"},{"from":26,"to":76,"value":0.2487562189,"title":"P(B|A): 24.88%","fnode":"Cerebral haemorrhage","tnode":"Thrombocytopenia"},{"from":26,"to":82,"value":0.4991708126,"title":"P(B|A): 49.92%","fnode":"Cerebral haemorrhage","tnode":"Death"},{"from":26,"to":99,"value":0.2852404643,"title":"P(B|A): 28.52%","fnode":"Cerebral haemorrhage","tnode":"Headache"},{"from":27,"to":68,"value":0.1203539823,"title":"P(B|A): 12.04%","fnode":"Insomnia","tnode":"Decreased appetite"},{"from":27,"to":86,"value":0.3415929204,"title":"P(B|A): 34.16%","fnode":"Insomnia","tnode":"Pain"},{"from":27,"to":89,"value":0.192920354,"title":"P(B|A): 19.29%","fnode":"Insomnia","tnode":"Pain in extremity"},{"from":27,"to":90,"value":0.2353982301,"title":"P(B|A): 23.54%","fnode":"Insomnia","tnode":"Arthralgia"},{"from":27,"to":91,"value":0.1681415929,"title":"P(B|A): 16.81%","fnode":"Insomnia","tnode":"Malaise"},{"from":27,"to":92,"value":0.189380531,"title":"P(B|A): 18.94%","fnode":"Insomnia","tnode":"Dizziness"},{"from":27,"to":93,"value":0.2495575221,"title":"P(B|A): 24.96%","fnode":"Insomnia","tnode":"Myalgia"},{"from":27,"to":94,"value":0.2778761062,"title":"P(B|A): 27.79%","fnode":"Insomnia","tnode":"Chills"},{"from":27,"to":95,"value":0.1522123894,"title":"P(B|A): 15.22%","fnode":"Insomnia","tnode":"Dyspnoea"},{"from":27,"to":96,"value":0.2743362832,"title":"P(B|A): 27.43%","fnode":"Insomnia","tnode":"Nausea"},{"from":27,"to":97,"value":0.3734513274,"title":"P(B|A): 37.35%","fnode":"Insomnia","tnode":"Fatigue"},{"from":27,"to":98,"value":0.3238938053,"title":"P(B|A): 32.39%","fnode":"Insomnia","tnode":"Pyrexia"},{"from":27,"to":99,"value":0.4566371681,"title":"P(B|A): 45.66%","fnode":"Insomnia","tnode":"Headache"},{"from":30,"to":71,"value":0.1256281407,"title":"P(B|A): 12.56%","fnode":"Oropharyngeal pain","tnode":"Abdominal pain"},{"from":30,"to":77,"value":0.2244556114,"title":"P(B|A): 22.45%","fnode":"Oropharyngeal pain","tnode":"Cough"},{"from":30,"to":86,"value":0.2780569514,"title":"P(B|A): 27.81%","fnode":"Oropharyngeal pain","tnode":"Pain"},{"from":30,"to":87,"value":0.1976549414,"title":"P(B|A): 19.77%","fnode":"Oropharyngeal pain","tnode":"Asthenia"},{"from":30,"to":89,"value":0.1474036851,"title":"P(B|A): 14.74%","fnode":"Oropharyngeal pain","tnode":"Pain in extremity"},{"from":30,"to":90,"value":0.2512562814,"title":"P(B|A): 25.13%","fnode":"Oropharyngeal pain","tnode":"Arthralgia"},{"from":30,"to":91,"value":0.1423785595,"title":"P(B|A): 14.24%","fnode":"Oropharyngeal pain","tnode":"Malaise"},{"from":30,"to":92,"value":0.256281407,"title":"P(B|A): 25.63%","fnode":"Oropharyngeal pain","tnode":"Dizziness"},{"from":30,"to":93,"value":0.3433835846,"title":"P(B|A): 34.34%","fnode":"Oropharyngeal pain","tnode":"Myalgia"},{"from":30,"to":94,"value":0.2830820771,"title":"P(B|A): 28.31%","fnode":"Oropharyngeal pain","tnode":"Chills"},{"from":30,"to":95,"value":0.2278056951,"title":"P(B|A): 22.78%","fnode":"Oropharyngeal pain","tnode":"Dyspnoea"},{"from":30,"to":96,"value":0.2613065327,"title":"P(B|A): 26.13%","fnode":"Oropharyngeal pain","tnode":"Nausea"},{"from":30,"to":97,"value":0.4857621441,"title":"P(B|A): 48.58%","fnode":"Oropharyngeal pain","tnode":"Fatigue"},{"from":30,"to":98,"value":0.4371859296,"title":"P(B|A): 43.72%","fnode":"Oropharyngeal pain","tnode":"Pyrexia"},{"from":30,"to":99,"value":0.5695142379,"title":"P(B|A): 56.95%","fnode":"Oropharyngeal pain","tnode":"Headache"},{"from":31,"to":55,"value":0.2118491921,"title":"P(B|A): 21.18%","fnode":"Urticaria","tnode":"Pruritus"},{"from":31,"to":72,"value":0.197486535,"title":"P(B|A): 19.75%","fnode":"Urticaria","tnode":"Rash"},{"from":31,"to":73,"value":0.1292639138,"title":"P(B|A): 12.93%","fnode":"Urticaria","tnode":"Anaphylactic reaction"},{"from":31,"to":95,"value":0.1669658887,"title":"P(B|A): 16.7%","fnode":"Urticaria","tnode":"Dyspnoea"},{"from":31,"to":96,"value":0.1454219031,"title":"P(B|A): 14.54%","fnode":"Urticaria","tnode":"Nausea"},{"from":31,"to":97,"value":0.1220825853,"title":"P(B|A): 12.21%","fnode":"Urticaria","tnode":"Fatigue"},{"from":31,"to":98,"value":0.2010771993,"title":"P(B|A): 20.11%","fnode":"Urticaria","tnode":"Pyrexia"},{"from":31,"to":99,"value":0.1992818671,"title":"P(B|A): 19.93%","fnode":"Urticaria","tnode":"Headache"},{"from":32,"to":68,"value":0.1258064516,"title":"P(B|A): 12.58%","fnode":"Somnolence","tnode":"Decreased appetite"},{"from":32,"to":82,"value":0.15,"title":"P(B|A): 15.0%","fnode":"Somnolence","tnode":"Death"},{"from":32,"to":86,"value":0.235483871,"title":"P(B|A): 23.55%","fnode":"Somnolence","tnode":"Pain"},{"from":32,"to":87,"value":0.1725806452,"title":"P(B|A): 17.26%","fnode":"Somnolence","tnode":"Asthenia"},{"from":32,"to":91,"value":0.1532258065,"title":"P(B|A): 15.32%","fnode":"Somnolence","tnode":"Malaise"},{"from":32,"to":92,"value":0.2080645161,"title":"P(B|A): 20.81%","fnode":"Somnolence","tnode":"Dizziness"},{"from":32,"to":93,"value":0.1629032258,"title":"P(B|A): 16.29%","fnode":"Somnolence","tnode":"Myalgia"},{"from":32,"to":94,"value":0.2016129032,"title":"P(B|A): 20.16%","fnode":"Somnolence","tnode":"Chills"},{"from":32,"to":96,"value":0.185483871,"title":"P(B|A): 18.55%","fnode":"Somnolence","tnode":"Nausea"},{"from":32,"to":97,"value":0.3419354839,"title":"P(B|A): 34.19%","fnode":"Somnolence","tnode":"Fatigue"},{"from":32,"to":98,"value":0.3548387097,"title":"P(B|A): 35.48%","fnode":"Somnolence","tnode":"Pyrexia"},{"from":32,"to":99,"value":0.3725806452,"title":"P(B|A): 37.26%","fnode":"Somnolence","tnode":"Headache"},{"from":33,"to":38,"value":0.1631944444,"title":"P(B|A): 16.32%","fnode":"Blood pressure increased","tnode":"Heart rate increased"},{"from":33,"to":86,"value":0.1284722222,"title":"P(B|A): 12.85%","fnode":"Blood pressure increased","tnode":"Pain"},{"from":33,"to":91,"value":0.1388888889,"title":"P(B|A): 13.89%","fnode":"Blood pressure increased","tnode":"Malaise"},{"from":33,"to":92,"value":0.2413194444,"title":"P(B|A): 24.13%","fnode":"Blood pressure increased","tnode":"Dizziness"},{"from":33,"to":95,"value":0.1579861111,"title":"P(B|A): 15.8%","fnode":"Blood pressure increased","tnode":"Dyspnoea"},{"from":33,"to":96,"value":0.1684027778,"title":"P(B|A): 16.84%","fnode":"Blood pressure increased","tnode":"Nausea"},{"from":33,"to":97,"value":0.1753472222,"title":"P(B|A): 17.53%","fnode":"Blood pressure increased","tnode":"Fatigue"},{"from":33,"to":98,"value":0.1527777778,"title":"P(B|A): 15.28%","fnode":"Blood pressure increased","tnode":"Pyrexia"},{"from":33,"to":99,"value":0.3194444444,"title":"P(B|A): 31.94%","fnode":"Blood pressure increased","tnode":"Headache"},{"from":34,"to":72,"value":0.1672535211,"title":"P(B|A): 16.73%","fnode":"Hypersensitivity","tnode":"Rash"},{"from":34,"to":92,"value":0.1496478873,"title":"P(B|A): 14.96%","fnode":"Hypersensitivity","tnode":"Dizziness"},{"from":34,"to":94,"value":0.1214788732,"title":"P(B|A): 12.15%","fnode":"Hypersensitivity","tnode":"Chills"},{"from":34,"to":95,"value":0.2059859155,"title":"P(B|A): 20.6%","fnode":"Hypersensitivity","tnode":"Dyspnoea"},{"from":34,"to":96,"value":0.125,"title":"P(B|A): 12.5%","fnode":"Hypersensitivity","tnode":"Nausea"},{"from":34,"to":97,"value":0.1355633803,"title":"P(B|A): 13.56%","fnode":"Hypersensitivity","tnode":"Fatigue"},{"from":34,"to":98,"value":0.1285211268,"title":"P(B|A): 12.85%","fnode":"Hypersensitivity","tnode":"Pyrexia"},{"from":34,"to":99,"value":0.213028169,"title":"P(B|A): 21.3%","fnode":"Hypersensitivity","tnode":"Headache"},{"from":35,"to":86,"value":0.1314199396,"title":"P(B|A): 13.14%","fnode":"Tinnitus","tnode":"Pain"},{"from":35,"to":92,"value":0.2719033233,"title":"P(B|A): 27.19%","fnode":"Tinnitus","tnode":"Dizziness"},{"from":35,"to":94,"value":0.1238670695,"title":"P(B|A): 12.39%","fnode":"Tinnitus","tnode":"Chills"},{"from":35,"to":96,"value":0.1903323263,"title":"P(B|A): 19.03%","fnode":"Tinnitus","tnode":"Nausea"},{"from":35,"to":97,"value":0.2235649547,"title":"P(B|A): 22.36%","fnode":"Tinnitus","tnode":"Fatigue"},{"from":35,"to":98,"value":0.1797583082,"title":"P(B|A): 17.98%","fnode":"Tinnitus","tnode":"Pyrexia"},{"from":35,"to":99,"value":0.3927492447,"title":"P(B|A): 39.27%","fnode":"Tinnitus","tnode":"Headache"},{"from":36,"to":95,"value":0.1565656566,"title":"P(B|A): 15.66%","fnode":"Atrial fibrillation","tnode":"Dyspnoea"},{"from":37,"to":61,"value":0.1569767442,"title":"P(B|A): 15.7%","fnode":"Neck pain","tnode":"Back pain"},{"from":37,"to":84,"value":0.1206395349,"title":"P(B|A): 12.06%","fnode":"Neck pain","tnode":"Chest pain"},{"from":37,"to":86,"value":0.3895348837,"title":"P(B|A): 38.95%","fnode":"Neck pain","tnode":"Pain"},{"from":37,"to":89,"value":0.2834302326,"title":"P(B|A): 28.34%","fnode":"Neck pain","tnode":"Pain in extremity"},{"from":37,"to":90,"value":0.3154069767,"title":"P(B|A): 31.54%","fnode":"Neck pain","tnode":"Arthralgia"},{"from":37,"to":92,"value":0.1773255814,"title":"P(B|A): 17.73%","fnode":"Neck pain","tnode":"Dizziness"},{"from":37,"to":93,"value":0.2063953488,"title":"P(B|A): 20.64%","fnode":"Neck pain","tnode":"Myalgia"},{"from":37,"to":94,"value":0.1889534884,"title":"P(B|A): 18.9%","fnode":"Neck pain","tnode":"Chills"},{"from":37,"to":96,"value":0.2369186047,"title":"P(B|A): 23.69%","fnode":"Neck pain","tnode":"Nausea"},{"from":37,"to":97,"value":0.2950581395,"title":"P(B|A): 29.51%","fnode":"Neck pain","tnode":"Fatigue"},{"from":37,"to":98,"value":0.2572674419,"title":"P(B|A): 25.73%","fnode":"Neck pain","tnode":"Pyrexia"},{"from":37,"to":99,"value":0.5639534884,"title":"P(B|A): 56.4%","fnode":"Neck pain","tnode":"Headache"},{"from":38,"to":33,"value":0.1482649842,"title":"P(B|A): 14.83%","fnode":"Heart rate increased","tnode":"Blood pressure increased"},{"from":38,"to":63,"value":0.141955836,"title":"P(B|A): 14.2%","fnode":"Heart rate increased","tnode":"Palpitations"},{"from":38,"to":84,"value":0.1356466877,"title":"P(B|A): 13.56%","fnode":"Heart rate increased","tnode":"Chest pain"},{"from":38,"to":86,"value":0.1892744479,"title":"P(B|A): 18.93%","fnode":"Heart rate increased","tnode":"Pain"},{"from":38,"to":87,"value":0.1261829653,"title":"P(B|A): 12.62%","fnode":"Heart rate increased","tnode":"Asthenia"},{"from":38,"to":91,"value":0.1403785489,"title":"P(B|A): 14.04%","fnode":"Heart rate increased","tnode":"Malaise"},{"from":38,"to":92,"value":0.2034700315,"title":"P(B|A): 20.35%","fnode":"Heart rate increased","tnode":"Dizziness"},{"from":38,"to":93,"value":0.1514195584,"title":"P(B|A): 15.14%","fnode":"Heart rate increased","tnode":"Myalgia"},{"from":38,"to":94,"value":0.1876971609,"title":"P(B|A): 18.77%","fnode":"Heart rate increased","tnode":"Chills"},{"from":38,"to":95,"value":0.2933753943,"title":"P(B|A): 29.34%","fnode":"Heart rate increased","tnode":"Dyspnoea"},{"from":38,"to":96,"value":0.1924290221,"title":"P(B|A): 19.24%","fnode":"Heart rate increased","tnode":"Nausea"},{"from":38,"to":97,"value":0.2681388013,"title":"P(B|A): 26.81%","fnode":"Heart rate increased","tnode":"Fatigue"},{"from":38,"to":98,"value":0.3485804416,"title":"P(B|A): 34.86%","fnode":"Heart rate increased","tnode":"Pyrexia"},{"from":38,"to":99,"value":0.3059936909,"title":"P(B|A): 30.6%","fnode":"Heart rate increased","tnode":"Headache"},{"from":39,"to":82,"value":0.1881355932,"title":"P(B|A): 18.81%","fnode":"Condition aggravated","tnode":"Death"},{"from":39,"to":86,"value":0.1661016949,"title":"P(B|A): 16.61%","fnode":"Condition aggravated","tnode":"Pain"},{"from":39,"to":95,"value":0.1610169492,"title":"P(B|A): 16.1%","fnode":"Condition aggravated","tnode":"Dyspnoea"},{"from":39,"to":97,"value":0.1711864407,"title":"P(B|A): 17.12%","fnode":"Condition aggravated","tnode":"Fatigue"},{"from":39,"to":98,"value":0.1491525424,"title":"P(B|A): 14.92%","fnode":"Condition aggravated","tnode":"Pyrexia"},{"from":39,"to":99,"value":0.1305084746,"title":"P(B|A): 13.05%","fnode":"Condition aggravated","tnode":"Headache"},{"from":40,"to":71,"value":1.0,"title":"P(B|A): 100.0%","fnode":"Abdominal pain upper","tnode":"Abdominal pain"},{"from":40,"to":81,"value":0.1491108071,"title":"P(B|A): 14.91%","fnode":"Abdominal pain upper","tnode":"Diarrhoea"},{"from":40,"to":86,"value":0.244870041,"title":"P(B|A): 24.49%","fnode":"Abdominal pain upper","tnode":"Pain"},{"from":40,"to":87,"value":0.1203830369,"title":"P(B|A): 12.04%","fnode":"Abdominal pain upper","tnode":"Asthenia"},{"from":40,"to":88,"value":0.1655266758,"title":"P(B|A): 16.55%","fnode":"Abdominal pain upper","tnode":"Vomiting"},{"from":40,"to":89,"value":0.1491108071,"title":"P(B|A): 14.91%","fnode":"Abdominal pain upper","tnode":"Pain in extremity"},{"from":40,"to":90,"value":0.1285909713,"title":"P(B|A): 12.86%","fnode":"Abdominal pain upper","tnode":"Arthralgia"},{"from":40,"to":91,"value":0.1244870041,"title":"P(B|A): 12.45%","fnode":"Abdominal pain upper","tnode":"Malaise"},{"from":40,"to":92,"value":0.1846785226,"title":"P(B|A): 18.47%","fnode":"Abdominal pain upper","tnode":"Dizziness"},{"from":40,"to":93,"value":0.146374829,"title":"P(B|A): 14.64%","fnode":"Abdominal pain upper","tnode":"Myalgia"},{"from":40,"to":94,"value":0.1901504788,"title":"P(B|A): 19.02%","fnode":"Abdominal pain upper","tnode":"Chills"},{"from":40,"to":96,"value":0.3529411765,"title":"P(B|A): 35.29%","fnode":"Abdominal pain upper","tnode":"Nausea"},{"from":40,"to":97,"value":0.3023255814,"title":"P(B|A): 30.23%","fnode":"Abdominal pain upper","tnode":"Fatigue"},{"from":40,"to":98,"value":0.2708618331,"title":"P(B|A): 27.09%","fnode":"Abdominal pain upper","tnode":"Pyrexia"},{"from":40,"to":99,"value":0.4021887825,"title":"P(B|A): 40.22%","fnode":"Abdominal pain upper","tnode":"Headache"},{"from":41,"to":86,"value":0.1782553729,"title":"P(B|A): 17.83%","fnode":"Vision blurred","tnode":"Pain"},{"from":41,"to":92,"value":0.2920353982,"title":"P(B|A): 29.2%","fnode":"Vision blurred","tnode":"Dizziness"},{"from":41,"to":93,"value":0.1226295828,"title":"P(B|A): 12.26%","fnode":"Vision blurred","tnode":"Myalgia"},{"from":41,"to":95,"value":0.1226295828,"title":"P(B|A): 12.26%","fnode":"Vision blurred","tnode":"Dyspnoea"},{"from":41,"to":96,"value":0.2275600506,"title":"P(B|A): 22.76%","fnode":"Vision blurred","tnode":"Nausea"},{"from":41,"to":97,"value":0.2743362832,"title":"P(B|A): 27.43%","fnode":"Vision blurred","tnode":"Fatigue"},{"from":41,"to":98,"value":0.1845764855,"title":"P(B|A): 18.46%","fnode":"Vision blurred","tnode":"Pyrexia"},{"from":41,"to":99,"value":0.5423514539,"title":"P(B|A): 54.24%","fnode":"Vision blurred","tnode":"Headache"},{"from":42,"to":90,"value":0.3939808482,"title":"P(B|A): 39.4%","fnode":"Injection site reaction","tnode":"Arthralgia"},{"from":42,"to":91,"value":0.4473324213,"title":"P(B|A): 44.73%","fnode":"Injection site reaction","tnode":"Malaise"},{"from":42,"to":93,"value":0.6566347469,"title":"P(B|A): 65.66%","fnode":"Injection site reaction","tnode":"Myalgia"},{"from":42,"to":94,"value":0.6990424077,"title":"P(B|A): 69.9%","fnode":"Injection site reaction","tnode":"Chills"},{"from":42,"to":96,"value":0.4336525308,"title":"P(B|A): 43.37%","fnode":"Injection site reaction","tnode":"Nausea"},{"from":42,"to":97,"value":0.7688098495,"title":"P(B|A): 76.88%","fnode":"Injection site reaction","tnode":"Fatigue"},{"from":42,"to":98,"value":0.6443228454,"title":"P(B|A): 64.43%","fnode":"Injection site reaction","tnode":"Pyrexia"},{"from":42,"to":99,"value":0.730506156,"title":"P(B|A): 73.05%","fnode":"Injection site reaction","tnode":"Headache"},{"from":43,"to":82,"value":0.8059259259,"title":"P(B|A): 80.59%","fnode":"Cardiac arrest","tnode":"Death"},{"from":43,"to":95,"value":0.1244444444,"title":"P(B|A): 12.44%","fnode":"Cardiac arrest","tnode":"Dyspnoea"},{"from":44,"to":60,"value":0.1266568483,"title":"P(B|A): 12.67%","fnode":"Gait disturbance","tnode":"Muscular weakness"},{"from":44,"to":79,"value":0.1487481591,"title":"P(B|A): 14.87%","fnode":"Gait disturbance","tnode":"Hypoaesthesia"},{"from":44,"to":80,"value":0.1251840943,"title":"P(B|A): 12.52%","fnode":"Gait disturbance","tnode":"Paraesthesia"},{"from":44,"to":86,"value":0.29455081,"title":"P(B|A): 29.46%","fnode":"Gait disturbance","tnode":"Pain"},{"from":44,"to":87,"value":0.175257732,"title":"P(B|A): 17.53%","fnode":"Gait disturbance","tnode":"Asthenia"},{"from":44,"to":89,"value":0.1840942563,"title":"P(B|A): 18.41%","fnode":"Gait disturbance","tnode":"Pain in extremity"},{"from":44,"to":90,"value":0.1384388807,"title":"P(B|A): 13.84%","fnode":"Gait disturbance","tnode":"Arthralgia"},{"from":44,"to":92,"value":0.1855670103,"title":"P(B|A): 18.56%","fnode":"Gait disturbance","tnode":"Dizziness"},{"from":44,"to":95,"value":0.1340206186,"title":"P(B|A): 13.4%","fnode":"Gait disturbance","tnode":"Dyspnoea"},{"from":44,"to":96,"value":0.1384388807,"title":"P(B|A): 13.84%","fnode":"Gait disturbance","tnode":"Nausea"},{"from":44,"to":97,"value":0.1973490427,"title":"P(B|A): 19.73%","fnode":"Gait disturbance","tnode":"Fatigue"},{"from":44,"to":98,"value":0.1634756996,"title":"P(B|A): 16.35%","fnode":"Gait disturbance","tnode":"Pyrexia"},{"from":44,"to":99,"value":0.2150220913,"title":"P(B|A): 21.5%","fnode":"Gait disturbance","tnode":"Headache"},{"from":45,"to":55,"value":0.2013888889,"title":"P(B|A): 20.14%","fnode":"Erythema","tnode":"Pruritus"},{"from":45,"to":56,"value":0.1361111111,"title":"P(B|A): 13.61%","fnode":"Erythema","tnode":"Peripheral swelling"},{"from":45,"to":72,"value":0.2083333333,"title":"P(B|A): 20.83%","fnode":"Erythema","tnode":"Rash"},{"from":45,"to":86,"value":0.2180555556,"title":"P(B|A): 21.81%","fnode":"Erythema","tnode":"Pain"},{"from":45,"to":90,"value":0.1333333333,"title":"P(B|A): 13.33%","fnode":"Erythema","tnode":"Arthralgia"},{"from":45,"to":91,"value":0.125,"title":"P(B|A): 12.5%","fnode":"Erythema","tnode":"Malaise"},{"from":45,"to":92,"value":0.1930555556,"title":"P(B|A): 19.31%","fnode":"Erythema","tnode":"Dizziness"},{"from":45,"to":94,"value":0.1375,"title":"P(B|A): 13.75%","fnode":"Erythema","tnode":"Chills"},{"from":45,"to":95,"value":0.1930555556,"title":"P(B|A): 19.31%","fnode":"Erythema","tnode":"Dyspnoea"},{"from":45,"to":96,"value":0.175,"title":"P(B|A): 17.5%","fnode":"Erythema","tnode":"Nausea"},{"from":45,"to":97,"value":0.1708333333,"title":"P(B|A): 17.08%","fnode":"Erythema","tnode":"Fatigue"},{"from":45,"to":98,"value":0.1958333333,"title":"P(B|A): 19.58%","fnode":"Erythema","tnode":"Pyrexia"},{"from":45,"to":99,"value":0.2583333333,"title":"P(B|A): 25.83%","fnode":"Erythema","tnode":"Headache"},{"from":46,"to":82,"value":0.2560455192,"title":"P(B|A): 25.6%","fnode":"Hypotension","tnode":"Death"},{"from":46,"to":87,"value":0.1507823613,"title":"P(B|A): 15.08%","fnode":"Hypotension","tnode":"Asthenia"},{"from":46,"to":88,"value":0.1365576102,"title":"P(B|A): 13.66%","fnode":"Hypotension","tnode":"Vomiting"},{"from":46,"to":91,"value":0.1365576102,"title":"P(B|A): 13.66%","fnode":"Hypotension","tnode":"Malaise"},{"from":46,"to":92,"value":0.1906116643,"title":"P(B|A): 19.06%","fnode":"Hypotension","tnode":"Dizziness"},{"from":46,"to":94,"value":0.13371266,"title":"P(B|A): 13.37%","fnode":"Hypotension","tnode":"Chills"},{"from":46,"to":95,"value":0.1749644381,"title":"P(B|A): 17.5%","fnode":"Hypotension","tnode":"Dyspnoea"},{"from":46,"to":96,"value":0.1578947368,"title":"P(B|A): 15.79%","fnode":"Hypotension","tnode":"Nausea"},{"from":46,"to":97,"value":0.146514936,"title":"P(B|A): 14.65%","fnode":"Hypotension","tnode":"Fatigue"},{"from":46,"to":98,"value":0.2418207681,"title":"P(B|A): 24.18%","fnode":"Hypotension","tnode":"Pyrexia"},{"from":46,"to":99,"value":0.1607396871,"title":"P(B|A): 16.07%","fnode":"Hypotension","tnode":"Headache"},{"from":47,"to":88,"value":0.1575829384,"title":"P(B|A): 15.76%","fnode":"Vertigo","tnode":"Vomiting"},{"from":47,"to":92,"value":0.2855450237,"title":"P(B|A): 28.55%","fnode":"Vertigo","tnode":"Dizziness"},{"from":47,"to":96,"value":0.3495260664,"title":"P(B|A): 34.95%","fnode":"Vertigo","tnode":"Nausea"},{"from":47,"to":97,"value":0.2109004739,"title":"P(B|A): 21.09%","fnode":"Vertigo","tnode":"Fatigue"},{"from":47,"to":98,"value":0.1706161137,"title":"P(B|A): 17.06%","fnode":"Vertigo","tnode":"Pyrexia"},{"from":47,"to":99,"value":0.3590047393,"title":"P(B|A): 35.9%","fnode":"Vertigo","tnode":"Headache"},{"from":48,"to":82,"value":0.1442663379,"title":"P(B|A): 14.43%","fnode":"Seizure","tnode":"Death"},{"from":48,"to":98,"value":0.1528976572,"title":"P(B|A): 15.29%","fnode":"Seizure","tnode":"Pyrexia"},{"from":48,"to":99,"value":0.2133168927,"title":"P(B|A): 21.33%","fnode":"Seizure","tnode":"Headache"},{"from":49,"to":86,"value":0.2933507171,"title":"P(B|A): 29.34%","fnode":"Lymphadenopathy","tnode":"Pain"},{"from":49,"to":89,"value":0.1538461538,"title":"P(B|A): 15.38%","fnode":"Lymphadenopathy","tnode":"Pain in extremity"},{"from":49,"to":90,"value":0.2242503259,"title":"P(B|A): 22.43%","fnode":"Lymphadenopathy","tnode":"Arthralgia"},{"from":49,"to":91,"value":0.1329856584,"title":"P(B|A): 13.3%","fnode":"Lymphadenopathy","tnode":"Malaise"},{"from":49,"to":92,"value":0.1747066493,"title":"P(B|A): 17.47%","fnode":"Lymphadenopathy","tnode":"Dizziness"},{"from":49,"to":93,"value":0.2777053455,"title":"P(B|A): 27.77%","fnode":"Lymphadenopathy","tnode":"Myalgia"},{"from":49,"to":94,"value":0.2307692308,"title":"P(B|A): 23.08%","fnode":"Lymphadenopathy","tnode":"Chills"},{"from":49,"to":96,"value":0.2099087353,"title":"P(B|A): 20.99%","fnode":"Lymphadenopathy","tnode":"Nausea"},{"from":49,"to":97,"value":0.3911342894,"title":"P(B|A): 39.11%","fnode":"Lymphadenopathy","tnode":"Fatigue"},{"from":49,"to":98,"value":0.3767926988,"title":"P(B|A): 37.68%","fnode":"Lymphadenopathy","tnode":"Pyrexia"},{"from":49,"to":99,"value":0.4654498044,"title":"P(B|A): 46.54%","fnode":"Lymphadenopathy","tnode":"Headache"},{"from":50,"to":86,"value":0.2082514735,"title":"P(B|A): 20.83%","fnode":"Migraine","tnode":"Pain"},{"from":50,"to":88,"value":0.1807465619,"title":"P(B|A): 18.07%","fnode":"Migraine","tnode":"Vomiting"},{"from":50,"to":90,"value":0.137524558,"title":"P(B|A): 13.75%","fnode":"Migraine","tnode":"Arthralgia"},{"from":50,"to":92,"value":0.2092337917,"title":"P(B|A): 20.92%","fnode":"Migraine","tnode":"Dizziness"},{"from":50,"to":93,"value":0.1601178782,"title":"P(B|A): 16.01%","fnode":"Migraine","tnode":"Myalgia"},{"from":50,"to":94,"value":0.2229862475,"title":"P(B|A): 22.3%","fnode":"Migraine","tnode":"Chills"},{"from":50,"to":96,"value":0.3320235756,"title":"P(B|A): 33.2%","fnode":"Migraine","tnode":"Nausea"},{"from":50,"to":97,"value":0.3565815324,"title":"P(B|A): 35.66%","fnode":"Migraine","tnode":"Fatigue"},{"from":50,"to":98,"value":0.3123772102,"title":"P(B|A): 31.24%","fnode":"Migraine","tnode":"Pyrexia"},{"from":50,"to":99,"value":0.3929273084,"title":"P(B|A): 39.29%","fnode":"Migraine","tnode":"Headache"},{"from":51,"to":84,"value":0.1678743961,"title":"P(B|A): 16.79%","fnode":"Chest discomfort","tnode":"Chest pain"},{"from":51,"to":86,"value":0.2016908213,"title":"P(B|A): 20.17%","fnode":"Chest discomfort","tnode":"Pain"},{"from":51,"to":91,"value":0.1497584541,"title":"P(B|A): 14.98%","fnode":"Chest discomfort","tnode":"Malaise"},{"from":51,"to":92,"value":0.2584541063,"title":"P(B|A): 25.85%","fnode":"Chest discomfort","tnode":"Dizziness"},{"from":51,"to":93,"value":0.1316425121,"title":"P(B|A): 13.16%","fnode":"Chest discomfort","tnode":"Myalgia"},{"from":51,"to":94,"value":0.1594202899,"title":"P(B|A): 15.94%","fnode":"Chest discomfort","tnode":"Chills"},{"from":51,"to":95,"value":0.4625603865,"title":"P(B|A): 46.26%","fnode":"Chest discomfort","tnode":"Dyspnoea"},{"from":51,"to":96,"value":0.2149758454,"title":"P(B|A): 21.5%","fnode":"Chest discomfort","tnode":"Nausea"},{"from":51,"to":97,"value":0.2983091787,"title":"P(B|A): 29.83%","fnode":"Chest discomfort","tnode":"Fatigue"},{"from":51,"to":98,"value":0.2427536232,"title":"P(B|A): 24.28%","fnode":"Chest discomfort","tnode":"Pyrexia"},{"from":51,"to":99,"value":0.3321256039,"title":"P(B|A): 33.21%","fnode":"Chest discomfort","tnode":"Headache"},{"from":52,"to":82,"value":0.2326530612,"title":"P(B|A): 23.27%","fnode":"Fall","tnode":"Death"},{"from":52,"to":87,"value":0.1823129252,"title":"P(B|A): 18.23%","fnode":"Fall","tnode":"Asthenia"},{"from":52,"to":92,"value":0.1714285714,"title":"P(B|A): 17.14%","fnode":"Fall","tnode":"Dizziness"},{"from":52,"to":98,"value":0.1578231293,"title":"P(B|A): 15.78%","fnode":"Fall","tnode":"Pyrexia"},{"from":53,"to":82,"value":0.391011236,"title":"P(B|A): 39.1%","fnode":"Myocardial infarction","tnode":"Death"},{"from":53,"to":84,"value":0.1292134831,"title":"P(B|A): 12.92%","fnode":"Myocardial infarction","tnode":"Chest pain"},{"from":54,"to":82,"value":0.3508583691,"title":"P(B|A): 35.09%","fnode":"Pneumonia","tnode":"Death"},{"from":54,"to":95,"value":0.2446351931,"title":"P(B|A): 24.46%","fnode":"Pneumonia","tnode":"Dyspnoea"},{"from":54,"to":98,"value":0.241416309,"title":"P(B|A): 24.14%","fnode":"Pneumonia","tnode":"Pyrexia"},{"from":55,"to":31,"value":0.1337868481,"title":"P(B|A): 13.38%","fnode":"Pruritus","tnode":"Urticaria"},{"from":55,"to":45,"value":0.164399093,"title":"P(B|A): 16.44%","fnode":"Pruritus","tnode":"Erythema"},{"from":55,"to":72,"value":0.2891156463,"title":"P(B|A): 28.91%","fnode":"Pruritus","tnode":"Rash"},{"from":55,"to":86,"value":0.1689342404,"title":"P(B|A): 16.89%","fnode":"Pruritus","tnode":"Pain"},{"from":55,"to":90,"value":0.141723356,"title":"P(B|A): 14.17%","fnode":"Pruritus","tnode":"Arthralgia"},{"from":55,"to":92,"value":0.1678004535,"title":"P(B|A): 16.78%","fnode":"Pruritus","tnode":"Dizziness"},{"from":55,"to":94,"value":0.1337868481,"title":"P(B|A): 13.38%","fnode":"Pruritus","tnode":"Chills"},{"from":55,"to":95,"value":0.1893424036,"title":"P(B|A): 18.93%","fnode":"Pruritus","tnode":"Dyspnoea"},{"from":55,"to":96,"value":0.1678004535,"title":"P(B|A): 16.78%","fnode":"Pruritus","tnode":"Nausea"},{"from":55,"to":97,"value":0.2346938776,"title":"P(B|A): 23.47%","fnode":"Pruritus","tnode":"Fatigue"},{"from":55,"to":98,"value":0.1836734694,"title":"P(B|A): 18.37%","fnode":"Pruritus","tnode":"Pyrexia"},{"from":55,"to":99,"value":0.298185941,"title":"P(B|A): 29.82%","fnode":"Pruritus","tnode":"Headache"},{"from":56,"to":65,"value":0.1342828077,"title":"P(B|A): 13.43%","fnode":"Peripheral swelling","tnode":"Deep vein thrombosis"},{"from":56,"to":86,"value":0.3682604273,"title":"P(B|A): 36.83%","fnode":"Peripheral swelling","tnode":"Pain"},{"from":56,"to":89,"value":0.2838250254,"title":"P(B|A): 28.38%","fnode":"Peripheral swelling","tnode":"Pain in extremity"},{"from":56,"to":90,"value":0.1759918616,"title":"P(B|A): 17.6%","fnode":"Peripheral swelling","tnode":"Arthralgia"},{"from":56,"to":94,"value":0.1414038657,"title":"P(B|A): 14.14%","fnode":"Peripheral swelling","tnode":"Chills"},{"from":56,"to":95,"value":0.1566632757,"title":"P(B|A): 15.67%","fnode":"Peripheral swelling","tnode":"Dyspnoea"},{"from":56,"to":96,"value":0.1393692777,"title":"P(B|A): 13.94%","fnode":"Peripheral swelling","tnode":"Nausea"},{"from":56,"to":97,"value":0.2319430315,"title":"P(B|A): 23.19%","fnode":"Peripheral swelling","tnode":"Fatigue"},{"from":56,"to":98,"value":0.2227873856,"title":"P(B|A): 22.28%","fnode":"Peripheral swelling","tnode":"Pyrexia"},{"from":56,"to":99,"value":0.2746693795,"title":"P(B|A): 27.47%","fnode":"Peripheral swelling","tnode":"Headache"},{"from":57,"to":86,"value":0.1891367604,"title":"P(B|A): 18.91%","fnode":"Influenza like illness","tnode":"Pain"},{"from":57,"to":90,"value":0.166828322,"title":"P(B|A): 16.68%","fnode":"Influenza like illness","tnode":"Arthralgia"},{"from":57,"to":91,"value":0.1677982541,"title":"P(B|A): 16.78%","fnode":"Influenza like illness","tnode":"Malaise"},{"from":57,"to":93,"value":0.2114451988,"title":"P(B|A): 21.14%","fnode":"Influenza like illness","tnode":"Myalgia"},{"from":57,"to":94,"value":0.2550921435,"title":"P(B|A): 25.51%","fnode":"Influenza like illness","tnode":"Chills"},{"from":57,"to":96,"value":0.2114451988,"title":"P(B|A): 21.14%","fnode":"Influenza like illness","tnode":"Nausea"},{"from":57,"to":97,"value":0.3773035887,"title":"P(B|A): 37.73%","fnode":"Influenza like illness","tnode":"Fatigue"},{"from":57,"to":98,"value":0.3404461688,"title":"P(B|A): 34.04%","fnode":"Influenza like illness","tnode":"Pyrexia"},{"from":57,"to":99,"value":0.4219204656,"title":"P(B|A): 42.19%","fnode":"Influenza like illness","tnode":"Headache"},{"from":58,"to":86,"value":0.2246220302,"title":"P(B|A): 22.46%","fnode":"Feeling abnormal","tnode":"Pain"},{"from":58,"to":90,"value":0.1252699784,"title":"P(B|A): 12.53%","fnode":"Feeling abnormal","tnode":"Arthralgia"},{"from":58,"to":91,"value":0.151187905,"title":"P(B|A): 15.12%","fnode":"Feeling abnormal","tnode":"Malaise"},{"from":58,"to":92,"value":0.3012958963,"title":"P(B|A): 30.13%","fnode":"Feeling abnormal","tnode":"Dizziness"},{"from":58,"to":93,"value":0.1371490281,"title":"P(B|A): 13.71%","fnode":"Feeling abnormal","tnode":"Myalgia"},{"from":58,"to":94,"value":0.2105831533,"title":"P(B|A): 21.06%","fnode":"Feeling abnormal","tnode":"Chills"},{"from":58,"to":95,"value":0.1663066955,"title":"P(B|A): 16.63%","fnode":"Feeling abnormal","tnode":"Dyspnoea"},{"from":58,"to":96,"value":0.2203023758,"title":"P(B|A): 22.03%","fnode":"Feeling abnormal","tnode":"Nausea"},{"from":58,"to":97,"value":0.3747300216,"title":"P(B|A): 37.47%","fnode":"Feeling abnormal","tnode":"Fatigue"},{"from":58,"to":98,"value":0.2613390929,"title":"P(B|A): 26.13%","fnode":"Feeling abnormal","tnode":"Pyrexia"},{"from":58,"to":99,"value":0.3844492441,"title":"P(B|A): 38.44%","fnode":"Feeling abnormal","tnode":"Headache"},{"from":59,"to":81,"value":0.1324626866,"title":"P(B|A): 13.25%","fnode":"Hyperhidrosis","tnode":"Diarrhoea"},{"from":59,"to":86,"value":0.2546641791,"title":"P(B|A): 25.47%","fnode":"Hyperhidrosis","tnode":"Pain"},{"from":59,"to":87,"value":0.1268656716,"title":"P(B|A): 12.69%","fnode":"Hyperhidrosis","tnode":"Asthenia"},{"from":59,"to":88,"value":0.1371268657,"title":"P(B|A): 13.71%","fnode":"Hyperhidrosis","tnode":"Vomiting"},{"from":59,"to":89,"value":0.1259328358,"title":"P(B|A): 12.59%","fnode":"Hyperhidrosis","tnode":"Pain in extremity"},{"from":59,"to":90,"value":0.1697761194,"title":"P(B|A): 16.98%","fnode":"Hyperhidrosis","tnode":"Arthralgia"},{"from":59,"to":91,"value":0.1641791045,"title":"P(B|A): 16.42%","fnode":"Hyperhidrosis","tnode":"Malaise"},{"from":59,"to":92,"value":0.2873134328,"title":"P(B|A): 28.73%","fnode":"Hyperhidrosis","tnode":"Dizziness"},{"from":59,"to":93,"value":0.2126865672,"title":"P(B|A): 21.27%","fnode":"Hyperhidrosis","tnode":"Myalgia"},{"from":59,"to":94,"value":0.4169776119,"title":"P(B|A): 41.7%","fnode":"Hyperhidrosis","tnode":"Chills"},{"from":59,"to":95,"value":0.1996268657,"title":"P(B|A): 19.96%","fnode":"Hyperhidrosis","tnode":"Dyspnoea"},{"from":59,"to":96,"value":0.3162313433,"title":"P(B|A): 31.62%","fnode":"Hyperhidrosis","tnode":"Nausea"},{"from":59,"to":97,"value":0.3526119403,"title":"P(B|A): 35.26%","fnode":"Hyperhidrosis","tnode":"Fatigue"},{"from":59,"to":98,"value":0.4375,"title":"P(B|A): 43.75%","fnode":"Hyperhidrosis","tnode":"Pyrexia"},{"from":59,"to":99,"value":0.4570895522,"title":"P(B|A): 45.71%","fnode":"Hyperhidrosis","tnode":"Headache"},{"from":60,"to":79,"value":0.169792695,"title":"P(B|A): 16.98%","fnode":"Muscular weakness","tnode":"Hypoaesthesia"},{"from":60,"to":80,"value":0.1786771964,"title":"P(B|A): 17.87%","fnode":"Muscular weakness","tnode":"Paraesthesia"},{"from":60,"to":86,"value":0.2546890424,"title":"P(B|A): 25.47%","fnode":"Muscular weakness","tnode":"Pain"},{"from":60,"to":89,"value":0.1717670286,"title":"P(B|A): 17.18%","fnode":"Muscular weakness","tnode":"Pain in extremity"},{"from":60,"to":90,"value":0.134254689,"title":"P(B|A): 13.43%","fnode":"Muscular weakness","tnode":"Arthralgia"},{"from":60,"to":92,"value":0.1707798618,"title":"P(B|A): 17.08%","fnode":"Muscular weakness","tnode":"Dizziness"},{"from":60,"to":93,"value":0.1707798618,"title":"P(B|A): 17.08%","fnode":"Muscular weakness","tnode":"Myalgia"},{"from":60,"to":94,"value":0.1224086871,"title":"P(B|A): 12.24%","fnode":"Muscular weakness","tnode":"Chills"},{"from":60,"to":96,"value":0.1490621915,"title":"P(B|A): 14.91%","fnode":"Muscular weakness","tnode":"Nausea"},{"from":60,"to":97,"value":0.2645607108,"title":"P(B|A): 26.46%","fnode":"Muscular weakness","tnode":"Fatigue"},{"from":60,"to":98,"value":0.1747285291,"title":"P(B|A): 17.47%","fnode":"Muscular weakness","tnode":"Pyrexia"},{"from":60,"to":99,"value":0.2971372162,"title":"P(B|A): 29.71%","fnode":"Muscular weakness","tnode":"Headache"},{"from":61,"to":71,"value":0.134469697,"title":"P(B|A): 13.45%","fnode":"Back pain","tnode":"Abdominal pain"},{"from":61,"to":84,"value":0.1600378788,"title":"P(B|A): 16.0%","fnode":"Back pain","tnode":"Chest pain"},{"from":61,"to":86,"value":0.3636363636,"title":"P(B|A): 36.36%","fnode":"Back pain","tnode":"Pain"},{"from":61,"to":89,"value":0.2367424242,"title":"P(B|A): 23.67%","fnode":"Back pain","tnode":"Pain in extremity"},{"from":61,"to":90,"value":0.2329545455,"title":"P(B|A): 23.3%","fnode":"Back pain","tnode":"Arthralgia"},{"from":61,"to":92,"value":0.1325757576,"title":"P(B|A): 13.26%","fnode":"Back pain","tnode":"Dizziness"},{"from":61,"to":93,"value":0.1742424242,"title":"P(B|A): 17.42%","fnode":"Back pain","tnode":"Myalgia"},{"from":61,"to":94,"value":0.1732954545,"title":"P(B|A): 17.33%","fnode":"Back pain","tnode":"Chills"},{"from":61,"to":95,"value":0.1524621212,"title":"P(B|A): 15.25%","fnode":"Back pain","tnode":"Dyspnoea"},{"from":61,"to":96,"value":0.1808712121,"title":"P(B|A): 18.09%","fnode":"Back pain","tnode":"Nausea"},{"from":61,"to":97,"value":0.2623106061,"title":"P(B|A): 26.23%","fnode":"Back pain","tnode":"Fatigue"},{"from":61,"to":98,"value":0.2670454545,"title":"P(B|A): 26.7%","fnode":"Back pain","tnode":"Pyrexia"},{"from":61,"to":99,"value":0.3579545455,"title":"P(B|A): 35.8%","fnode":"Back pain","tnode":"Headache"},{"from":62,"to":82,"value":0.2068965517,"title":"P(B|A): 20.69%","fnode":"Loss of consciousness","tnode":"Death"},{"from":62,"to":86,"value":0.121703854,"title":"P(B|A): 12.17%","fnode":"Loss of consciousness","tnode":"Pain"},{"from":62,"to":88,"value":0.1206896552,"title":"P(B|A): 12.07%","fnode":"Loss of consciousness","tnode":"Vomiting"},{"from":62,"to":91,"value":0.1379310345,"title":"P(B|A): 13.79%","fnode":"Loss of consciousness","tnode":"Malaise"},{"from":62,"to":92,"value":0.2079107505,"title":"P(B|A): 20.79%","fnode":"Loss of consciousness","tnode":"Dizziness"},{"from":62,"to":96,"value":0.1470588235,"title":"P(B|A): 14.71%","fnode":"Loss of consciousness","tnode":"Nausea"},{"from":62,"to":97,"value":0.1348884381,"title":"P(B|A): 13.49%","fnode":"Loss of consciousness","tnode":"Fatigue"},{"from":62,"to":98,"value":0.1490872211,"title":"P(B|A): 14.91%","fnode":"Loss of consciousness","tnode":"Pyrexia"},{"from":62,"to":99,"value":0.2058823529,"title":"P(B|A): 20.59%","fnode":"Loss of consciousness","tnode":"Headache"},{"from":63,"to":84,"value":0.135483871,"title":"P(B|A): 13.55%","fnode":"Palpitations","tnode":"Chest pain"},{"from":63,"to":86,"value":0.1677419355,"title":"P(B|A): 16.77%","fnode":"Palpitations","tnode":"Pain"},{"from":63,"to":91,"value":0.1216589862,"title":"P(B|A): 12.17%","fnode":"Palpitations","tnode":"Malaise"},{"from":63,"to":92,"value":0.2958525346,"title":"P(B|A): 29.59%","fnode":"Palpitations","tnode":"Dizziness"},{"from":63,"to":93,"value":0.1235023041,"title":"P(B|A): 12.35%","fnode":"Palpitations","tnode":"Myalgia"},{"from":63,"to":94,"value":0.1935483871,"title":"P(B|A): 19.35%","fnode":"Palpitations","tnode":"Chills"},{"from":63,"to":95,"value":0.2866359447,"title":"P(B|A): 28.66%","fnode":"Palpitations","tnode":"Dyspnoea"},{"from":63,"to":96,"value":0.2396313364,"title":"P(B|A): 23.96%","fnode":"Palpitations","tnode":"Nausea"},{"from":63,"to":97,"value":0.2838709677,"title":"P(B|A): 28.39%","fnode":"Palpitations","tnode":"Fatigue"},{"from":63,"to":98,"value":0.264516129,"title":"P(B|A): 26.45%","fnode":"Palpitations","tnode":"Pyrexia"},{"from":63,"to":99,"value":0.3594470046,"title":"P(B|A): 35.94%","fnode":"Palpitations","tnode":"Headache"},{"from":64,"to":82,"value":0.1300738007,"title":"P(B|A): 13.01%","fnode":"Confusional state","tnode":"Death"},{"from":64,"to":87,"value":0.1383763838,"title":"P(B|A): 13.84%","fnode":"Confusional state","tnode":"Asthenia"},{"from":64,"to":92,"value":0.1549815498,"title":"P(B|A): 15.5%","fnode":"Confusional state","tnode":"Dizziness"},{"from":64,"to":94,"value":0.1254612546,"title":"P(B|A): 12.55%","fnode":"Confusional state","tnode":"Chills"},{"from":64,"to":95,"value":0.1236162362,"title":"P(B|A): 12.36%","fnode":"Confusional state","tnode":"Dyspnoea"},{"from":64,"to":96,"value":0.1623616236,"title":"P(B|A): 16.24%","fnode":"Confusional state","tnode":"Nausea"},{"from":64,"to":97,"value":0.2361623616,"title":"P(B|A): 23.62%","fnode":"Confusional state","tnode":"Fatigue"},{"from":64,"to":98,"value":0.221402214,"title":"P(B|A): 22.14%","fnode":"Confusional state","tnode":"Pyrexia"},{"from":64,"to":99,"value":0.2915129151,"title":"P(B|A): 29.15%","fnode":"Confusional state","tnode":"Headache"},{"from":65,"to":85,"value":0.4254016832,"title":"P(B|A): 42.54%","fnode":"Deep vein thrombosis","tnode":"Pulmonary embolism"},{"from":65,"to":86,"value":0.1514919663,"title":"P(B|A): 15.15%","fnode":"Deep vein thrombosis","tnode":"Pain"},{"from":65,"to":89,"value":0.1315990819,"title":"P(B|A): 13.16%","fnode":"Deep vein thrombosis","tnode":"Pain in extremity"},{"from":66,"to":74,"value":0.1285714286,"title":"P(B|A): 12.86%","fnode":"Tachycardia","tnode":"Hypertension"},{"from":66,"to":86,"value":0.1495238095,"title":"P(B|A): 14.95%","fnode":"Tachycardia","tnode":"Pain"},{"from":66,"to":87,"value":0.1495238095,"title":"P(B|A): 14.95%","fnode":"Tachycardia","tnode":"Asthenia"},{"from":66,"to":92,"value":0.2219047619,"title":"P(B|A): 22.19%","fnode":"Tachycardia","tnode":"Dizziness"},{"from":66,"to":93,"value":0.14,"title":"P(B|A): 14.0%","fnode":"Tachycardia","tnode":"Myalgia"},{"from":66,"to":94,"value":0.1838095238,"title":"P(B|A): 18.38%","fnode":"Tachycardia","tnode":"Chills"},{"from":66,"to":95,"value":0.2780952381,"title":"P(B|A): 27.81%","fnode":"Tachycardia","tnode":"Dyspnoea"},{"from":66,"to":96,"value":0.2123809524,"title":"P(B|A): 21.24%","fnode":"Tachycardia","tnode":"Nausea"},{"from":66,"to":97,"value":0.2019047619,"title":"P(B|A): 20.19%","fnode":"Tachycardia","tnode":"Fatigue"},{"from":66,"to":98,"value":0.299047619,"title":"P(B|A): 29.9%","fnode":"Tachycardia","tnode":"Pyrexia"},{"from":66,"to":99,"value":0.300952381,"title":"P(B|A): 30.1%","fnode":"Tachycardia","tnode":"Headache"},{"from":67,"to":86,"value":0.2066895369,"title":"P(B|A): 20.67%","fnode":"Tremor","tnode":"Pain"},{"from":67,"to":87,"value":0.1320754717,"title":"P(B|A): 13.21%","fnode":"Tremor","tnode":"Asthenia"},{"from":67,"to":88,"value":0.1320754717,"title":"P(B|A): 13.21%","fnode":"Tremor","tnode":"Vomiting"},{"from":67,"to":91,"value":0.1234991424,"title":"P(B|A): 12.35%","fnode":"Tremor","tnode":"Malaise"},{"from":67,"to":92,"value":0.2409948542,"title":"P(B|A): 24.1%","fnode":"Tremor","tnode":"Dizziness"},{"from":67,"to":93,"value":0.1552315609,"title":"P(B|A): 15.52%","fnode":"Tremor","tnode":"Myalgia"},{"from":67,"to":94,"value":0.2761578045,"title":"P(B|A): 27.62%","fnode":"Tremor","tnode":"Chills"},{"from":67,"to":95,"value":0.1509433962,"title":"P(B|A): 15.09%","fnode":"Tremor","tnode":"Dyspnoea"},{"from":67,"to":96,"value":0.2332761578,"title":"P(B|A): 23.33%","fnode":"Tremor","tnode":"Nausea"},{"from":67,"to":97,"value":0.2684391081,"title":"P(B|A): 26.84%","fnode":"Tremor","tnode":"Fatigue"},{"from":67,"to":98,"value":0.3516295026,"title":"P(B|A): 35.16%","fnode":"Tremor","tnode":"Pyrexia"},{"from":67,"to":99,"value":0.4005145798,"title":"P(B|A): 40.05%","fnode":"Tremor","tnode":"Headache"},{"from":68,"to":71,"value":0.1318027211,"title":"P(B|A): 13.18%","fnode":"Decreased appetite","tnode":"Abdominal pain"},{"from":68,"to":82,"value":0.1632653061,"title":"P(B|A): 16.33%","fnode":"Decreased appetite","tnode":"Death"},{"from":68,"to":86,"value":0.2542517007,"title":"P(B|A): 25.43%","fnode":"Decreased appetite","tnode":"Pain"},{"from":68,"to":87,"value":0.2338435374,"title":"P(B|A): 23.38%","fnode":"Decreased appetite","tnode":"Asthenia"},{"from":68,"to":88,"value":0.1454081633,"title":"P(B|A): 14.54%","fnode":"Decreased appetite","tnode":"Vomiting"},{"from":68,"to":89,"value":0.1241496599,"title":"P(B|A): 12.41%","fnode":"Decreased appetite","tnode":"Pain in extremity"},{"from":68,"to":90,"value":0.1641156463,"title":"P(B|A): 16.41%","fnode":"Decreased appetite","tnode":"Arthralgia"},{"from":68,"to":91,"value":0.1964285714,"title":"P(B|A): 19.64%","fnode":"Decreased appetite","tnode":"Malaise"},{"from":68,"to":92,"value":0.2176870748,"title":"P(B|A): 21.77%","fnode":"Decreased appetite","tnode":"Dizziness"},{"from":68,"to":93,"value":0.2193877551,"title":"P(B|A): 21.94%","fnode":"Decreased appetite","tnode":"Myalgia"},{"from":68,"to":94,"value":0.268707483,"title":"P(B|A): 26.87%","fnode":"Decreased appetite","tnode":"Chills"},{"from":68,"to":95,"value":0.1743197279,"title":"P(B|A): 17.43%","fnode":"Decreased appetite","tnode":"Dyspnoea"},{"from":68,"to":96,"value":0.3673469388,"title":"P(B|A): 36.73%","fnode":"Decreased appetite","tnode":"Nausea"},{"from":68,"to":97,"value":0.4761904762,"title":"P(B|A): 47.62%","fnode":"Decreased appetite","tnode":"Fatigue"},{"from":68,"to":98,"value":0.4039115646,"title":"P(B|A): 40.39%","fnode":"Decreased appetite","tnode":"Pyrexia"},{"from":68,"to":99,"value":0.425170068,"title":"P(B|A): 42.52%","fnode":"Decreased appetite","tnode":"Headache"},{"from":69,"to":86,"value":0.2902298851,"title":"P(B|A): 29.02%","fnode":"Vaccination site pain","tnode":"Pain"},{"from":69,"to":89,"value":0.1475095785,"title":"P(B|A): 14.75%","fnode":"Vaccination site pain","tnode":"Pain in extremity"},{"from":69,"to":90,"value":0.2528735632,"title":"P(B|A): 25.29%","fnode":"Vaccination site pain","tnode":"Arthralgia"},{"from":69,"to":91,"value":0.1570881226,"title":"P(B|A): 15.71%","fnode":"Vaccination site pain","tnode":"Malaise"},{"from":69,"to":92,"value":0.1609195402,"title":"P(B|A): 16.09%","fnode":"Vaccination site pain","tnode":"Dizziness"},{"from":69,"to":93,"value":0.3247126437,"title":"P(B|A): 32.47%","fnode":"Vaccination site pain","tnode":"Myalgia"},{"from":69,"to":94,"value":0.2538314176,"title":"P(B|A): 25.38%","fnode":"Vaccination site pain","tnode":"Chills"},{"from":69,"to":96,"value":0.2318007663,"title":"P(B|A): 23.18%","fnode":"Vaccination site pain","tnode":"Nausea"},{"from":69,"to":97,"value":0.3505747126,"title":"P(B|A): 35.06%","fnode":"Vaccination site pain","tnode":"Fatigue"},{"from":69,"to":98,"value":0.398467433,"title":"P(B|A): 39.85%","fnode":"Vaccination site pain","tnode":"Pyrexia"},{"from":69,"to":99,"value":0.4291187739,"title":"P(B|A): 42.91%","fnode":"Vaccination site pain","tnode":"Headache"},{"from":70,"to":92,"value":0.2336283186,"title":"P(B|A): 23.36%","fnode":"Syncope","tnode":"Dizziness"},{"from":70,"to":94,"value":0.1265486726,"title":"P(B|A): 12.65%","fnode":"Syncope","tnode":"Chills"},{"from":70,"to":96,"value":0.182300885,"title":"P(B|A): 18.23%","fnode":"Syncope","tnode":"Nausea"},{"from":70,"to":97,"value":0.1451327434,"title":"P(B|A): 14.51%","fnode":"Syncope","tnode":"Fatigue"},{"from":70,"to":98,"value":0.1982300885,"title":"P(B|A): 19.82%","fnode":"Syncope","tnode":"Pyrexia"},{"from":70,"to":99,"value":0.2371681416,"title":"P(B|A): 23.72%","fnode":"Syncope","tnode":"Headache"},{"from":71,"to":40,"value":0.3635007459,"title":"P(B|A): 36.35%","fnode":"Abdominal pain","tnode":"Abdominal pain upper"},{"from":71,"to":81,"value":0.1670810542,"title":"P(B|A): 16.71%","fnode":"Abdominal pain","tnode":"Diarrhoea"},{"from":71,"to":86,"value":0.223769269,"title":"P(B|A): 22.38%","fnode":"Abdominal pain","tnode":"Pain"},{"from":71,"to":87,"value":0.1218299354,"title":"P(B|A): 12.18%","fnode":"Abdominal pain","tnode":"Asthenia"},{"from":71,"to":88,"value":0.1854798608,"title":"P(B|A): 18.55%","fnode":"Abdominal pain","tnode":"Vomiting"},{"from":71,"to":90,"value":0.1541521631,"title":"P(B|A): 15.42%","fnode":"Abdominal pain","tnode":"Arthralgia"},{"from":71,"to":92,"value":0.187966186,"title":"P(B|A): 18.8%","fnode":"Abdominal pain","tnode":"Dizziness"},{"from":71,"to":93,"value":0.1690701144,"title":"P(B|A): 16.91%","fnode":"Abdominal pain","tnode":"Myalgia"},{"from":71,"to":94,"value":0.1959224267,"title":"P(B|A): 19.59%","fnode":"Abdominal pain","tnode":"Chills"},{"from":71,"to":96,"value":0.3212332173,"title":"P(B|A): 32.12%","fnode":"Abdominal pain","tnode":"Nausea"},{"from":71,"to":97,"value":0.281949279,"title":"P(B|A): 28.19%","fnode":"Abdominal pain","tnode":"Fatigue"},{"from":71,"to":98,"value":0.2993535554,"title":"P(B|A): 29.94%","fnode":"Abdominal pain","tnode":"Pyrexia"},{"from":71,"to":99,"value":0.3988065639,"title":"P(B|A): 39.88%","fnode":"Abdominal pain","tnode":"Headache"},{"from":72,"to":55,"value":0.167542707,"title":"P(B|A): 16.75%","fnode":"Rash","tnode":"Pruritus"},{"from":72,"to":86,"value":0.1944809461,"title":"P(B|A): 19.45%","fnode":"Rash","tnode":"Pain"},{"from":72,"to":92,"value":0.1425755585,"title":"P(B|A): 14.26%","fnode":"Rash","tnode":"Dizziness"},{"from":72,"to":94,"value":0.1327201051,"title":"P(B|A): 13.27%","fnode":"Rash","tnode":"Chills"},{"from":72,"to":95,"value":0.1557161629,"title":"P(B|A): 15.57%","fnode":"Rash","tnode":"Dyspnoea"},{"from":72,"to":96,"value":0.1438896189,"title":"P(B|A): 14.39%","fnode":"Rash","tnode":"Nausea"},{"from":72,"to":97,"value":0.1905387648,"title":"P(B|A): 19.05%","fnode":"Rash","tnode":"Fatigue"},{"from":72,"to":98,"value":0.2240473062,"title":"P(B|A): 22.4%","fnode":"Rash","tnode":"Pyrexia"},{"from":72,"to":99,"value":0.2667542707,"title":"P(B|A): 26.68%","fnode":"Rash","tnode":"Headache"},{"from":73,"to":95,"value":0.243062201,"title":"P(B|A): 24.31%","fnode":"Anaphylactic reaction","tnode":"Dyspnoea"},{"from":73,"to":96,"value":0.1387559809,"title":"P(B|A): 13.88%","fnode":"Anaphylactic reaction","tnode":"Nausea"},{"from":74,"to":91,"value":0.1274763135,"title":"P(B|A): 12.75%","fnode":"Hypertension","tnode":"Malaise"},{"from":74,"to":92,"value":0.2049956934,"title":"P(B|A): 20.5%","fnode":"Hypertension","tnode":"Dizziness"},{"from":74,"to":95,"value":0.1403962102,"title":"P(B|A): 14.04%","fnode":"Hypertension","tnode":"Dyspnoea"},{"from":74,"to":96,"value":0.1438415159,"title":"P(B|A): 14.38%","fnode":"Hypertension","tnode":"Nausea"},{"from":74,"to":97,"value":0.1679586563,"title":"P(B|A): 16.8%","fnode":"Hypertension","tnode":"Fatigue"},{"from":74,"to":98,"value":0.1800172265,"title":"P(B|A): 18.0%","fnode":"Hypertension","tnode":"Pyrexia"},{"from":74,"to":99,"value":0.3204134367,"title":"P(B|A): 32.04%","fnode":"Hypertension","tnode":"Headache"},{"from":75,"to":82,"value":0.1525542337,"title":"P(B|A): 15.26%","fnode":"Thrombosis","tnode":"Death"},{"from":75,"to":85,"value":0.122463261,"title":"P(B|A): 12.25%","fnode":"Thrombosis","tnode":"Pulmonary embolism"},{"from":75,"to":86,"value":0.155353394,"title":"P(B|A): 15.54%","fnode":"Thrombosis","tnode":"Pain"},{"from":75,"to":99,"value":0.1238628411,"title":"P(B|A): 12.39%","fnode":"Thrombosis","tnode":"Headache"},{"from":76,"to":10,"value":0.1501416431,"title":"P(B|A): 15.01%","fnode":"Thrombocytopenia","tnode":"Cerebral venous sinus thrombosis"},{"from":76,"to":82,"value":0.1869688385,"title":"P(B|A): 18.7%","fnode":"Thrombocytopenia","tnode":"Death"},{"from":76,"to":85,"value":0.2062322946,"title":"P(B|A): 20.62%","fnode":"Thrombocytopenia","tnode":"Pulmonary embolism"},{"from":76,"to":99,"value":0.2538243626,"title":"P(B|A): 25.38%","fnode":"Thrombocytopenia","tnode":"Headache"},{"from":77,"to":82,"value":0.1232492997,"title":"P(B|A): 12.32%","fnode":"Cough","tnode":"Death"},{"from":77,"to":86,"value":0.175070028,"title":"P(B|A): 17.51%","fnode":"Cough","tnode":"Pain"},{"from":77,"to":87,"value":0.1274509804,"title":"P(B|A): 12.75%","fnode":"Cough","tnode":"Asthenia"},{"from":77,"to":90,"value":0.1260504202,"title":"P(B|A): 12.61%","fnode":"Cough","tnode":"Arthralgia"},{"from":77,"to":91,"value":0.1218487395,"title":"P(B|A): 12.18%","fnode":"Cough","tnode":"Malaise"},{"from":77,"to":93,"value":0.1659663866,"title":"P(B|A): 16.6%","fnode":"Cough","tnode":"Myalgia"},{"from":77,"to":94,"value":0.1925770308,"title":"P(B|A): 19.26%","fnode":"Cough","tnode":"Chills"},{"from":77,"to":95,"value":0.3844537815,"title":"P(B|A): 38.45%","fnode":"Cough","tnode":"Dyspnoea"},{"from":77,"to":96,"value":0.1645658263,"title":"P(B|A): 16.46%","fnode":"Cough","tnode":"Nausea"},{"from":77,"to":97,"value":0.2598039216,"title":"P(B|A): 25.98%","fnode":"Cough","tnode":"Fatigue"},{"from":77,"to":98,"value":0.4075630252,"title":"P(B|A): 40.76%","fnode":"Cough","tnode":"Pyrexia"},{"from":77,"to":99,"value":0.2913165266,"title":"P(B|A): 29.13%","fnode":"Cough","tnode":"Headache"},{"from":78,"to":23,"value":0.2103395844,"title":"P(B|A): 21.03%","fnode":"COVID-19","tnode":"Drug ineffective"},{"from":78,"to":82,"value":0.3537759757,"title":"P(B|A): 35.38%","fnode":"COVID-19","tnode":"Death"},{"from":78,"to":95,"value":0.126710593,"title":"P(B|A): 12.67%","fnode":"COVID-19","tnode":"Dyspnoea"},{"from":78,"to":98,"value":0.1414090218,"title":"P(B|A): 14.14%","fnode":"COVID-19","tnode":"Pyrexia"},{"from":79,"to":80,"value":0.2762691854,"title":"P(B|A): 27.63%","fnode":"Hypoaesthesia","tnode":"Paraesthesia"},{"from":79,"to":86,"value":0.225501771,"title":"P(B|A): 22.55%","fnode":"Hypoaesthesia","tnode":"Pain"},{"from":79,"to":89,"value":0.147579693,"title":"P(B|A): 14.76%","fnode":"Hypoaesthesia","tnode":"Pain in extremity"},{"from":79,"to":92,"value":0.1871310508,"title":"P(B|A): 18.71%","fnode":"Hypoaesthesia","tnode":"Dizziness"},{"from":79,"to":94,"value":0.1239669421,"title":"P(B|A): 12.4%","fnode":"Hypoaesthesia","tnode":"Chills"},{"from":79,"to":95,"value":0.13459268,"title":"P(B|A): 13.46%","fnode":"Hypoaesthesia","tnode":"Dyspnoea"},{"from":79,"to":96,"value":0.1629279811,"title":"P(B|A): 16.29%","fnode":"Hypoaesthesia","tnode":"Nausea"},{"from":79,"to":97,"value":0.1906729634,"title":"P(B|A): 19.07%","fnode":"Hypoaesthesia","tnode":"Fatigue"},{"from":79,"to":98,"value":0.194214876,"title":"P(B|A): 19.42%","fnode":"Hypoaesthesia","tnode":"Pyrexia"},{"from":79,"to":99,"value":0.3530106257,"title":"P(B|A): 35.3%","fnode":"Hypoaesthesia","tnode":"Headache"},{"from":80,"to":79,"value":0.2424870466,"title":"P(B|A): 24.25%","fnode":"Paraesthesia","tnode":"Hypoaesthesia"},{"from":80,"to":86,"value":0.229015544,"title":"P(B|A): 22.9%","fnode":"Paraesthesia","tnode":"Pain"},{"from":80,"to":89,"value":0.1461139896,"title":"P(B|A): 14.61%","fnode":"Paraesthesia","tnode":"Pain in extremity"},{"from":80,"to":90,"value":0.1341968912,"title":"P(B|A): 13.42%","fnode":"Paraesthesia","tnode":"Arthralgia"},{"from":80,"to":92,"value":0.1953367876,"title":"P(B|A): 19.53%","fnode":"Paraesthesia","tnode":"Dizziness"},{"from":80,"to":93,"value":0.1409326425,"title":"P(B|A): 14.09%","fnode":"Paraesthesia","tnode":"Myalgia"},{"from":80,"to":94,"value":0.1310880829,"title":"P(B|A): 13.11%","fnode":"Paraesthesia","tnode":"Chills"},{"from":80,"to":95,"value":0.1284974093,"title":"P(B|A): 12.85%","fnode":"Paraesthesia","tnode":"Dyspnoea"},{"from":80,"to":96,"value":0.1761658031,"title":"P(B|A): 17.62%","fnode":"Paraesthesia","tnode":"Nausea"},{"from":80,"to":97,"value":0.2238341969,"title":"P(B|A): 22.38%","fnode":"Paraesthesia","tnode":"Fatigue"},{"from":80,"to":98,"value":0.1772020725,"title":"P(B|A): 17.72%","fnode":"Paraesthesia","tnode":"Pyrexia"},{"from":80,"to":99,"value":0.3575129534,"title":"P(B|A): 35.75%","fnode":"Paraesthesia","tnode":"Headache"},{"from":81,"to":71,"value":0.1798715203,"title":"P(B|A): 17.99%","fnode":"Diarrhoea","tnode":"Abdominal pain"},{"from":81,"to":86,"value":0.1879014989,"title":"P(B|A): 18.79%","fnode":"Diarrhoea","tnode":"Pain"},{"from":81,"to":87,"value":0.136509636,"title":"P(B|A): 13.65%","fnode":"Diarrhoea","tnode":"Asthenia"},{"from":81,"to":88,"value":0.2815845824,"title":"P(B|A): 28.16%","fnode":"Diarrhoea","tnode":"Vomiting"},{"from":81,"to":90,"value":0.1541755889,"title":"P(B|A): 15.42%","fnode":"Diarrhoea","tnode":"Arthralgia"},{"from":81,"to":91,"value":0.1386509636,"title":"P(B|A): 13.87%","fnode":"Diarrhoea","tnode":"Malaise"},{"from":81,"to":92,"value":0.1739828694,"title":"P(B|A): 17.4%","fnode":"Diarrhoea","tnode":"Dizziness"},{"from":81,"to":93,"value":0.1707708779,"title":"P(B|A): 17.08%","fnode":"Diarrhoea","tnode":"Myalgia"},{"from":81,"to":94,"value":0.2360813704,"title":"P(B|A): 23.61%","fnode":"Diarrhoea","tnode":"Chills"},{"from":81,"to":95,"value":0.1215203426,"title":"P(B|A): 12.15%","fnode":"Diarrhoea","tnode":"Dyspnoea"},{"from":81,"to":96,"value":0.3158458244,"title":"P(B|A): 31.58%","fnode":"Diarrhoea","tnode":"Nausea"},{"from":81,"to":97,"value":0.2997858672,"title":"P(B|A): 29.98%","fnode":"Diarrhoea","tnode":"Fatigue"},{"from":81,"to":98,"value":0.3731263383,"title":"P(B|A): 37.31%","fnode":"Diarrhoea","tnode":"Pyrexia"},{"from":81,"to":99,"value":0.3795503212,"title":"P(B|A): 37.96%","fnode":"Diarrhoea","tnode":"Headache"},{"from":83,"to":82,"value":0.1516996449,"title":"P(B|A): 15.17%","fnode":"Cerebrovascular accident","tnode":"Death"},{"from":84,"to":85,"value":0.1203374778,"title":"P(B|A): 12.03%","fnode":"Chest pain","tnode":"Pulmonary embolism"},{"from":84,"to":86,"value":0.2220248668,"title":"P(B|A): 22.2%","fnode":"Chest pain","tnode":"Pain"},{"from":84,"to":89,"value":0.1261101243,"title":"P(B|A): 12.61%","fnode":"Chest pain","tnode":"Pain in extremity"},{"from":84,"to":92,"value":0.1509769094,"title":"P(B|A): 15.1%","fnode":"Chest pain","tnode":"Dizziness"},{"from":84,"to":95,"value":0.3396980462,"title":"P(B|A): 33.97%","fnode":"Chest pain","tnode":"Dyspnoea"},{"from":84,"to":96,"value":0.1301065719,"title":"P(B|A): 13.01%","fnode":"Chest pain","tnode":"Nausea"},{"from":84,"to":97,"value":0.1976021314,"title":"P(B|A): 19.76%","fnode":"Chest pain","tnode":"Fatigue"},{"from":84,"to":98,"value":0.210035524,"title":"P(B|A): 21.0%","fnode":"Chest pain","tnode":"Pyrexia"},{"from":84,"to":99,"value":0.2797513321,"title":"P(B|A): 27.98%","fnode":"Chest pain","tnode":"Headache"},{"from":85,"to":65,"value":0.1631455399,"title":"P(B|A): 16.31%","fnode":"Pulmonary embolism","tnode":"Deep vein thrombosis"},{"from":85,"to":82,"value":0.125,"title":"P(B|A): 12.5%","fnode":"Pulmonary embolism","tnode":"Death"},{"from":85,"to":95,"value":0.2150821596,"title":"P(B|A): 21.51%","fnode":"Pulmonary embolism","tnode":"Dyspnoea"},{"from":86,"to":89,"value":0.5567913718,"title":"P(B|A): 55.68%","fnode":"Pain","tnode":"Pain in extremity"},{"from":86,"to":90,"value":0.1841927873,"title":"P(B|A): 18.42%","fnode":"Pain","tnode":"Arthralgia"},{"from":86,"to":92,"value":0.160768453,"title":"P(B|A): 16.08%","fnode":"Pain","tnode":"Dizziness"},{"from":86,"to":93,"value":0.1703741153,"title":"P(B|A): 17.04%","fnode":"Pain","tnode":"Myalgia"},{"from":86,"to":94,"value":0.2145264577,"title":"P(B|A): 21.45%","fnode":"Pain","tnode":"Chills"},{"from":86,"to":95,"value":0.1220087631,"title":"P(B|A): 12.2%","fnode":"Pain","tnode":"Dyspnoea"},{"from":86,"to":96,"value":0.1968318166,"title":"P(B|A): 19.68%","fnode":"Pain","tnode":"Nausea"},{"from":86,"to":97,"value":0.2925513987,"title":"P(B|A): 29.26%","fnode":"Pain","tnode":"Fatigue"},{"from":86,"to":98,"value":0.3201887428,"title":"P(B|A): 32.02%","fnode":"Pain","tnode":"Pyrexia"},{"from":86,"to":99,"value":0.4000674082,"title":"P(B|A): 40.01%","fnode":"Pain","tnode":"Headache"},{"from":87,"to":86,"value":0.2063546293,"title":"P(B|A): 20.64%","fnode":"Asthenia","tnode":"Pain"},{"from":87,"to":90,"value":0.1578407926,"title":"P(B|A): 15.78%","fnode":"Asthenia","tnode":"Arthralgia"},{"from":87,"to":91,"value":0.1229928254,"title":"P(B|A): 12.3%","fnode":"Asthenia","tnode":"Malaise"},{"from":87,"to":92,"value":0.2207037923,"title":"P(B|A): 22.07%","fnode":"Asthenia","tnode":"Dizziness"},{"from":87,"to":93,"value":0.2265117868,"title":"P(B|A): 22.65%","fnode":"Asthenia","tnode":"Myalgia"},{"from":87,"to":94,"value":0.2271950803,"title":"P(B|A): 22.72%","fnode":"Asthenia","tnode":"Chills"},{"from":87,"to":95,"value":0.1697984284,"title":"P(B|A): 16.98%","fnode":"Asthenia","tnode":"Dyspnoea"},{"from":87,"to":96,"value":0.2248035531,"title":"P(B|A): 22.48%","fnode":"Asthenia","tnode":"Nausea"},{"from":87,"to":97,"value":0.3413050905,"title":"P(B|A): 34.13%","fnode":"Asthenia","tnode":"Fatigue"},{"from":87,"to":98,"value":0.3385719166,"title":"P(B|A): 33.86%","fnode":"Asthenia","tnode":"Pyrexia"},{"from":87,"to":99,"value":0.3723949436,"title":"P(B|A): 37.24%","fnode":"Asthenia","tnode":"Headache"},{"from":88,"to":71,"value":0.1206729214,"title":"P(B|A): 12.07%","fnode":"Vomiting","tnode":"Abdominal pain"},{"from":88,"to":81,"value":0.1701714655,"title":"P(B|A): 17.02%","fnode":"Vomiting","tnode":"Diarrhoea"},{"from":88,"to":82,"value":0.1410546749,"title":"P(B|A): 14.11%","fnode":"Vomiting","tnode":"Death"},{"from":88,"to":86,"value":0.1478485927,"title":"P(B|A): 14.78%","fnode":"Vomiting","tnode":"Pain"},{"from":88,"to":91,"value":0.1245551601,"title":"P(B|A): 12.46%","fnode":"Vomiting","tnode":"Malaise"},{"from":88,"to":92,"value":0.1831122614,"title":"P(B|A): 18.31%","fnode":"Vomiting","tnode":"Dizziness"},{"from":88,"to":93,"value":0.1226140408,"title":"P(B|A): 12.26%","fnode":"Vomiting","tnode":"Myalgia"},{"from":88,"to":94,"value":0.2002588159,"title":"P(B|A): 20.03%","fnode":"Vomiting","tnode":"Chills"},{"from":88,"to":96,"value":0.4273697832,"title":"P(B|A): 42.74%","fnode":"Vomiting","tnode":"Nausea"},{"from":88,"to":97,"value":0.2067292138,"title":"P(B|A): 20.67%","fnode":"Vomiting","tnode":"Fatigue"},{"from":88,"to":98,"value":0.3319314138,"title":"P(B|A): 33.19%","fnode":"Vomiting","tnode":"Pyrexia"},{"from":88,"to":99,"value":0.3827240375,"title":"P(B|A): 38.27%","fnode":"Vomiting","tnode":"Headache"},{"from":89,"to":86,"value":1.0,"title":"P(B|A): 100.0%","fnode":"Pain in extremity","tnode":"Pain"},{"from":89,"to":90,"value":0.1903753027,"title":"P(B|A): 19.04%","fnode":"Pain in extremity","tnode":"Arthralgia"},{"from":89,"to":92,"value":0.1446731235,"title":"P(B|A): 14.47%","fnode":"Pain in extremity","tnode":"Dizziness"},{"from":89,"to":93,"value":0.1601089588,"title":"P(B|A): 16.01%","fnode":"Pain in extremity","tnode":"Myalgia"},{"from":89,"to":94,"value":0.1737288136,"title":"P(B|A): 17.37%","fnode":"Pain in extremity","tnode":"Chills"},{"from":89,"to":95,"value":0.1204600484,"title":"P(B|A): 12.05%","fnode":"Pain in extremity","tnode":"Dyspnoea"},{"from":89,"to":96,"value":0.1843220339,"title":"P(B|A): 18.43%","fnode":"Pain in extremity","tnode":"Nausea"},{"from":89,"to":97,"value":0.2778450363,"title":"P(B|A): 27.78%","fnode":"Pain in extremity","tnode":"Fatigue"},{"from":89,"to":98,"value":0.2584745763,"title":"P(B|A): 25.85%","fnode":"Pain in extremity","tnode":"Pyrexia"},{"from":89,"to":99,"value":0.3686440678,"title":"P(B|A): 36.86%","fnode":"Pain in extremity","tnode":"Headache"},{"from":90,"to":86,"value":0.2710813492,"title":"P(B|A): 27.11%","fnode":"Arthralgia","tnode":"Pain"},{"from":90,"to":89,"value":0.1560019841,"title":"P(B|A): 15.6%","fnode":"Arthralgia","tnode":"Pain in extremity"},{"from":90,"to":91,"value":0.1773313492,"title":"P(B|A): 17.73%","fnode":"Arthralgia","tnode":"Malaise"},{"from":90,"to":92,"value":0.1644345238,"title":"P(B|A): 16.44%","fnode":"Arthralgia","tnode":"Dizziness"},{"from":90,"to":93,"value":0.4677579365,"title":"P(B|A): 46.78%","fnode":"Arthralgia","tnode":"Myalgia"},{"from":90,"to":94,"value":0.3467261905,"title":"P(B|A): 34.67%","fnode":"Arthralgia","tnode":"Chills"},{"from":90,"to":96,"value":0.2757936508,"title":"P(B|A): 27.58%","fnode":"Arthralgia","tnode":"Nausea"},{"from":90,"to":97,"value":0.4593253968,"title":"P(B|A): 45.93%","fnode":"Arthralgia","tnode":"Fatigue"},{"from":90,"to":98,"value":0.4352678571,"title":"P(B|A): 43.53%","fnode":"Arthralgia","tnode":"Pyrexia"},{"from":90,"to":99,"value":0.544890873,"title":"P(B|A): 54.49%","fnode":"Arthralgia","tnode":"Headache"},{"from":91,"to":82,"value":0.1286003032,"title":"P(B|A): 12.86%","fnode":"Malaise","tnode":"Death"},{"from":91,"to":86,"value":0.1579080344,"title":"P(B|A): 15.79%","fnode":"Malaise","tnode":"Pain"},{"from":91,"to":90,"value":0.1806467913,"title":"P(B|A): 18.06%","fnode":"Malaise","tnode":"Arthralgia"},{"from":91,"to":92,"value":0.1642243557,"title":"P(B|A): 16.42%","fnode":"Malaise","tnode":"Dizziness"},{"from":91,"to":93,"value":0.2650328449,"title":"P(B|A): 26.5%","fnode":"Malaise","tnode":"Myalgia"},{"from":91,"to":94,"value":0.3006568974,"title":"P(B|A): 30.07%","fnode":"Malaise","tnode":"Chills"},{"from":91,"to":96,"value":0.2998989389,"title":"P(B|A): 29.99%","fnode":"Malaise","tnode":"Nausea"},{"from":91,"to":97,"value":0.3840323396,"title":"P(B|A): 38.4%","fnode":"Malaise","tnode":"Fatigue"},{"from":91,"to":98,"value":0.3777160182,"title":"P(B|A): 37.77%","fnode":"Malaise","tnode":"Pyrexia"},{"from":91,"to":99,"value":0.4540171804,"title":"P(B|A): 45.4%","fnode":"Malaise","tnode":"Headache"},{"from":92,"to":86,"value":0.2054263566,"title":"P(B|A): 20.54%","fnode":"Dizziness","tnode":"Pain"},{"from":92,"to":87,"value":0.1391042205,"title":"P(B|A): 13.91%","fnode":"Dizziness","tnode":"Asthenia"},{"from":92,"to":88,"value":0.1218776916,"title":"P(B|A): 12.19%","fnode":"Dizziness","tnode":"Vomiting"},{"from":92,"to":90,"value":0.1427648579,"title":"P(B|A): 14.28%","fnode":"Dizziness","tnode":"Arthralgia"},{"from":92,"to":91,"value":0.1399655469,"title":"P(B|A): 14.0%","fnode":"Dizziness","tnode":"Malaise"},{"from":92,"to":93,"value":0.1905684755,"title":"P(B|A): 19.06%","fnode":"Dizziness","tnode":"Myalgia"},{"from":92,"to":94,"value":0.2241602067,"title":"P(B|A): 22.42%","fnode":"Dizziness","tnode":"Chills"},{"from":92,"to":95,"value":0.1485788114,"title":"P(B|A): 14.86%","fnode":"Dizziness","tnode":"Dyspnoea"},{"from":92,"to":96,"value":0.334625323,"title":"P(B|A): 33.46%","fnode":"Dizziness","tnode":"Nausea"},{"from":92,"to":97,"value":0.3337639966,"title":"P(B|A): 33.38%","fnode":"Dizziness","tnode":"Fatigue"},{"from":92,"to":98,"value":0.273255814,"title":"P(B|A): 27.33%","fnode":"Dizziness","tnode":"Pyrexia"},{"from":92,"to":99,"value":0.4857881137,"title":"P(B|A): 48.58%","fnode":"Dizziness","tnode":"Headache"},{"from":93,"to":86,"value":0.1965396579,"title":"P(B|A): 19.65%","fnode":"Myalgia","tnode":"Pain"},{"from":93,"to":87,"value":0.1288880249,"title":"P(B|A): 12.89%","fnode":"Myalgia","tnode":"Asthenia"},{"from":93,"to":90,"value":0.3666407465,"title":"P(B|A): 36.66%","fnode":"Myalgia","tnode":"Arthralgia"},{"from":93,"to":91,"value":0.2039269051,"title":"P(B|A): 20.39%","fnode":"Myalgia","tnode":"Malaise"},{"from":93,"to":92,"value":0.1720451011,"title":"P(B|A): 17.2%","fnode":"Myalgia","tnode":"Dizziness"},{"from":93,"to":94,"value":0.4109642302,"title":"P(B|A): 41.1%","fnode":"Myalgia","tnode":"Chills"},{"from":93,"to":96,"value":0.3055987558,"title":"P(B|A): 30.56%","fnode":"Myalgia","tnode":"Nausea"},{"from":93,"to":97,"value":0.4914463453,"title":"P(B|A): 49.14%","fnode":"Myalgia","tnode":"Fatigue"},{"from":93,"to":98,"value":0.5513219285,"title":"P(B|A): 55.13%","fnode":"Myalgia","tnode":"Pyrexia"},{"from":93,"to":99,"value":0.6106143079,"title":"P(B|A): 61.06%","fnode":"Myalgia","tnode":"Headache"},{"from":94,"to":86,"value":0.2322992701,"title":"P(B|A): 23.23%","fnode":"Chills","tnode":"Pain"},{"from":94,"to":87,"value":0.121350365,"title":"P(B|A): 12.14%","fnode":"Chills","tnode":"Asthenia"},{"from":94,"to":90,"value":0.2551094891,"title":"P(B|A): 25.51%","fnode":"Chills","tnode":"Arthralgia"},{"from":94,"to":91,"value":0.2171532847,"title":"P(B|A): 21.72%","fnode":"Chills","tnode":"Malaise"},{"from":94,"to":92,"value":0.1899635036,"title":"P(B|A): 19.0%","fnode":"Chills","tnode":"Dizziness"},{"from":94,"to":93,"value":0.3857664234,"title":"P(B|A): 38.58%","fnode":"Chills","tnode":"Myalgia"},{"from":94,"to":96,"value":0.35,"title":"P(B|A): 35.0%","fnode":"Chills","tnode":"Nausea"},{"from":94,"to":97,"value":0.4795620438,"title":"P(B|A): 47.96%","fnode":"Chills","tnode":"Fatigue"},{"from":94,"to":98,"value":0.6275547445,"title":"P(B|A): 62.76%","fnode":"Chills","tnode":"Pyrexia"},{"from":94,"to":99,"value":0.6056569343,"title":"P(B|A): 60.57%","fnode":"Chills","tnode":"Headache"},{"from":95,"to":82,"value":0.1560355268,"title":"P(B|A): 15.6%","fnode":"Dyspnoea","tnode":"Death"},{"from":95,"to":84,"value":0.1544206702,"title":"P(B|A): 15.44%","fnode":"Dyspnoea","tnode":"Chest pain"},{"from":95,"to":85,"value":0.1479612434,"title":"P(B|A): 14.8%","fnode":"Dyspnoea","tnode":"Pulmonary embolism"},{"from":95,"to":86,"value":0.1461445297,"title":"P(B|A): 14.61%","fnode":"Dyspnoea","tnode":"Pain"},{"from":95,"to":92,"value":0.1392813888,"title":"P(B|A): 13.93%","fnode":"Dyspnoea","tnode":"Dizziness"},{"from":95,"to":96,"value":0.1336293904,"title":"P(B|A): 13.36%","fnode":"Dyspnoea","tnode":"Nausea"},{"from":95,"to":97,"value":0.2099313686,"title":"P(B|A): 20.99%","fnode":"Dyspnoea","tnode":"Fatigue"},{"from":95,"to":98,"value":0.2184093662,"title":"P(B|A): 21.84%","fnode":"Dyspnoea","tnode":"Pyrexia"},{"from":95,"to":99,"value":0.2238595075,"title":"P(B|A): 22.39%","fnode":"Dyspnoea","tnode":"Headache"},{"from":96,"to":86,"value":0.2048044889,"title":"P(B|A): 20.48%","fnode":"Nausea","tnode":"Pain"},{"from":96,"to":88,"value":0.2316324741,"title":"P(B|A): 23.16%","fnode":"Nausea","tnode":"Vomiting"},{"from":96,"to":90,"value":0.1949850956,"title":"P(B|A): 19.5%","fnode":"Nausea","tnode":"Arthralgia"},{"from":96,"to":91,"value":0.2081360687,"title":"P(B|A): 20.81%","fnode":"Nausea","tnode":"Malaise"},{"from":96,"to":92,"value":0.2724881641,"title":"P(B|A): 27.25%","fnode":"Nausea","tnode":"Dizziness"},{"from":96,"to":93,"value":0.2756443977,"title":"P(B|A): 27.56%","fnode":"Nausea","tnode":"Myalgia"},{"from":96,"to":94,"value":0.3363142206,"title":"P(B|A): 33.63%","fnode":"Nausea","tnode":"Chills"},{"from":96,"to":97,"value":0.4087322462,"title":"P(B|A): 40.87%","fnode":"Nausea","tnode":"Fatigue"},{"from":96,"to":98,"value":0.3982114676,"title":"P(B|A): 39.82%","fnode":"Nausea","tnode":"Pyrexia"},{"from":96,"to":99,"value":0.5693494652,"title":"P(B|A): 56.93%","fnode":"Nausea","tnode":"Headache"},{"from":97,"to":86,"value":0.2226782966,"title":"P(B|A): 22.27%","fnode":"Fatigue","tnode":"Pain"},{"from":97,"to":87,"value":0.1281426372,"title":"P(B|A): 12.81%","fnode":"Fatigue","tnode":"Asthenia"},{"from":97,"to":90,"value":0.2375577219,"title":"P(B|A): 23.76%","fnode":"Fatigue","tnode":"Arthralgia"},{"from":97,"to":91,"value":0.1949717804,"title":"P(B|A): 19.5%","fnode":"Fatigue","tnode":"Malaise"},{"from":97,"to":92,"value":0.1988199076,"title":"P(B|A): 19.88%","fnode":"Fatigue","tnode":"Dizziness"},{"from":97,"to":93,"value":0.3242688558,"title":"P(B|A): 32.43%","fnode":"Fatigue","tnode":"Myalgia"},{"from":97,"to":94,"value":0.3370959466,"title":"P(B|A): 33.71%","fnode":"Fatigue","tnode":"Chills"},{"from":97,"to":95,"value":0.1334017445,"title":"P(B|A): 13.34%","fnode":"Fatigue","tnode":"Dyspnoea"},{"from":97,"to":96,"value":0.2989994869,"title":"P(B|A): 29.9%","fnode":"Fatigue","tnode":"Nausea"},{"from":97,"to":98,"value":0.4104669061,"title":"P(B|A): 41.05%","fnode":"Fatigue","tnode":"Pyrexia"},{"from":97,"to":99,"value":0.5427142124,"title":"P(B|A): 54.27%","fnode":"Fatigue","tnode":"Headache"},{"from":98,"to":86,"value":0.2060290609,"title":"P(B|A): 20.6%","fnode":"Pyrexia","tnode":"Pain"},{"from":98,"to":90,"value":0.1903057905,"title":"P(B|A): 19.03%","fnode":"Pyrexia","tnode":"Arthralgia"},{"from":98,"to":91,"value":0.1621123401,"title":"P(B|A): 16.21%","fnode":"Pyrexia","tnode":"Malaise"},{"from":98,"to":92,"value":0.1376057254,"title":"P(B|A): 13.76%","fnode":"Pyrexia","tnode":"Dizziness"},{"from":98,"to":93,"value":0.3075254825,"title":"P(B|A): 30.75%","fnode":"Pyrexia","tnode":"Myalgia"},{"from":98,"to":94,"value":0.3729126003,"title":"P(B|A): 37.29%","fnode":"Pyrexia","tnode":"Chills"},{"from":98,"to":96,"value":0.246258946,"title":"P(B|A): 24.63%","fnode":"Pyrexia","tnode":"Nausea"},{"from":98,"to":97,"value":0.3469963132,"title":"P(B|A): 34.7%","fnode":"Pyrexia","tnode":"Fatigue"},{"from":98,"to":99,"value":0.4887226198,"title":"P(B|A): 48.87%","fnode":"Pyrexia","tnode":"Headache"},{"from":99,"to":86,"value":0.2074630779,"title":"P(B|A): 20.75%","fnode":"Headache","tnode":"Pain"},{"from":99,"to":90,"value":0.1919951062,"title":"P(B|A): 19.2%","fnode":"Headache","tnode":"Arthralgia"},{"from":99,"to":91,"value":0.157039238,"title":"P(B|A): 15.7%","fnode":"Headache","tnode":"Malaise"},{"from":99,"to":92,"value":0.1971510967,"title":"P(B|A): 19.72%","fnode":"Headache","tnode":"Dizziness"},{"from":99,"to":93,"value":0.2744909552,"title":"P(B|A): 27.45%","fnode":"Headache","tnode":"Myalgia"},{"from":99,"to":94,"value":0.2900463165,"title":"P(B|A): 29.0%","fnode":"Headache","tnode":"Chills"},{"from":99,"to":96,"value":0.2837542602,"title":"P(B|A): 28.38%","fnode":"Headache","tnode":"Nausea"},{"from":99,"to":97,"value":0.3697456961,"title":"P(B|A): 36.97%","fnode":"Headache","tnode":"Fatigue"},{"from":99,"to":98,"value":0.3938652451,"title":"P(B|A): 39.39%","fnode":"Headache","tnode":"Pyrexia"}],[{"id":0,"value":0.0017876317,"label":"Contusion","title":"P(A): 0.178%"},{"id":1,"value":0.0017994313,"label":"Hemiparesis","title":"P(A): 0.179%"},{"id":2,"value":0.0017994313,"label":"Acute myocardial infarction","title":"P(A): 0.179%"},{"id":3,"value":0.0018407297,"label":"Epistaxis","title":"P(A): 0.184%"},{"id":4,"value":0.001858429,"label":"Sudden death","title":"P(A): 0.185%"},{"id":5,"value":0.0018643288,"label":"Dysphagia","title":"P(A): 0.186%"},{"id":6,"value":0.0018997274,"label":"Cerebral infarction","title":"P(A): 0.189%"},{"id":7,"value":0.0019705247,"label":"Cardiac failure","title":"P(A): 0.197%"},{"id":8,"value":0.0019941238,"label":"Feeling cold","title":"P(A): 0.199%"},{"id":9,"value":0.0019941238,"label":"Musculoskeletal stiffness","title":"P(A): 0.199%"},{"id":10,"value":0.0020059234,"label":"Cerebral venous sinus thrombosis","title":"P(A): 0.200%"},{"id":11,"value":0.0020236227,"label":"Unresponsive to stimuli","title":"P(A): 0.202%"},{"id":12,"value":0.0020590213,"label":"Dysarthria","title":"P(A): 0.205%"},{"id":13,"value":0.0020590213,"label":"Visual impairment","title":"P(A): 0.205%"},{"id":14,"value":0.0021121193,"label":"Feeling hot","title":"P(A): 0.211%"},{"id":15,"value":0.002147518,"label":"Aphasia","title":"P(A): 0.214%"},{"id":16,"value":0.0021534177,"label":"Balance disorder","title":"P(A): 0.215%"},{"id":17,"value":0.0022478141,"label":"Guillain-Barre syndrome","title":"P(A): 0.224%"},{"id":18,"value":0.0022478141,"label":"Injection site pain","title":"P(A): 0.224%"},{"id":19,"value":0.0022596137,"label":"Facial paralysis","title":"P(A): 0.225%"},{"id":20,"value":0.002277313,"label":"Oxygen saturation decreased","title":"P(A): 0.227%"},{"id":21,"value":0.0022832128,"label":"Illness","title":"P(A): 0.228%"},{"id":22,"value":0.0023068119,"label":"General physical health deterioration","title":"P(A): 0.230%"},{"id":23,"value":0.0023245112,"label":"Drug ineffective","title":"P(A): 0.232%"},{"id":24,"value":0.0023835089,"label":"Lethargy","title":"P(A): 0.238%"},{"id":25,"value":0.0024366069,"label":"Muscle spasms","title":"P(A): 0.243%"},{"id":26,"value":0.0025546024,"label":"Cerebral haemorrhage","title":"P(A): 0.255%"},{"id":27,"value":0.0025723017,"label":"Insomnia","title":"P(A): 0.257%"},{"id":28,"value":0.0026077004,"label":"Transient ischaemic attack","title":"P(A): 0.260%"},{"id":29,"value":0.0026371993,"label":"Ischaemic stroke","title":"P(A): 0.263%"},{"id":30,"value":0.0026666981,"label":"Oropharyngeal pain","title":"P(A): 0.266%"},{"id":31,"value":0.0027433952,"label":"Urticaria","title":"P(A): 0.274%"},{"id":32,"value":0.0028141925,"label":"Somnolence","title":"P(A): 0.281%"},{"id":33,"value":0.002825992,"label":"Blood pressure increased","title":"P(A): 0.282%"},{"id":34,"value":0.0028377916,"label":"Hypersensitivity","title":"P(A): 0.283%"},{"id":35,"value":0.0028554909,"label":"Tinnitus","title":"P(A): 0.285%"},{"id":36,"value":0.0030442837,"label":"Atrial fibrillation","title":"P(A): 0.304%"},{"id":37,"value":0.0030737826,"label":"Neck pain","title":"P(A): 0.307%"},{"id":38,"value":0.0031091812,"label":"Heart rate increased","title":"P(A): 0.310%"},{"id":39,"value":0.0031740788,"label":"Condition aggravated","title":"P(A): 0.317%"},{"id":40,"value":0.0031858783,"label":"Abdominal pain upper","title":"P(A): 0.318%"},{"id":41,"value":0.0031976778,"label":"Vision blurred","title":"P(A): 0.319%"},{"id":42,"value":0.0032566756,"label":"Injection site reaction","title":"P(A): 0.325%"},{"id":43,"value":0.0032743749,"label":"Cardiac arrest","title":"P(A): 0.327%"},{"id":44,"value":0.0034218693,"label":"Gait disturbance","title":"P(A): 0.342%"},{"id":45,"value":0.0034513682,"label":"Erythema","title":"P(A): 0.345%"},{"id":46,"value":0.0034985664,"label":"Hypotension","title":"P(A): 0.349%"},{"id":47,"value":0.0035752634,"label":"Vertigo","title":"P(A): 0.357%"},{"id":48,"value":0.003716858,"label":"Seizure","title":"P(A): 0.371%"},{"id":49,"value":0.0037817555,"label":"Lymphadenopathy","title":"P(A): 0.378%"},{"id":50,"value":0.0037935551,"label":"Migraine","title":"P(A): 0.379%"},{"id":51,"value":0.0038466531,"label":"Chest discomfort","title":"P(A): 0.384%"},{"id":52,"value":0.0039823479,"label":"Fall","title":"P(A): 0.398%"},{"id":53,"value":0.0040118467,"label":"Myocardial infarction","title":"P(A): 0.401%"},{"id":54,"value":0.0040590449,"label":"Pneumonia","title":"P(A): 0.405%"},{"id":55,"value":0.004241938,"label":"Pruritus","title":"P(A): 0.424%"},{"id":56,"value":0.0042714368,"label":"Peripheral swelling","title":"P(A): 0.427%"},{"id":57,"value":0.0043894323,"label":"Influenza like illness","title":"P(A): 0.438%"},{"id":58,"value":0.0044779289,"label":"Feeling abnormal","title":"P(A): 0.447%"},{"id":59,"value":0.0046549222,"label":"Hyperhidrosis","title":"P(A): 0.465%"},{"id":60,"value":0.0047257195,"label":"Muscular weakness","title":"P(A): 0.472%"},{"id":61,"value":0.0047965168,"label":"Back pain","title":"P(A): 0.479%"},{"id":62,"value":0.0048260156,"label":"Loss of consciousness","title":"P(A): 0.482%"},{"id":63,"value":0.0049027127,"label":"Palpitations","title":"P(A): 0.490%"},{"id":64,"value":0.0050207082,"label":"Confusional state","title":"P(A): 0.502%"},{"id":65,"value":0.0050384075,"label":"Deep vein thrombosis","title":"P(A): 0.503%"},{"id":66,"value":0.0050443073,"label":"Tachycardia","title":"P(A): 0.504%"},{"id":67,"value":0.0051092048,"label":"Tremor","title":"P(A): 0.510%"},{"id":68,"value":0.0052389999,"label":"Decreased appetite","title":"P(A): 0.523%"},{"id":69,"value":0.0052743985,"label":"Vaccination site pain","title":"P(A): 0.527%"},{"id":70,"value":0.0053510956,"label":"Syncope","title":"P(A): 0.535%"},{"id":71,"value":0.0053510956,"label":"Abdominal pain","title":"P(A): 0.535%"},{"id":72,"value":0.0054100933,"label":"Rash","title":"P(A): 0.541%"},{"id":73,"value":0.00549859,"label":"Anaphylactic reaction","title":"P(A): 0.549%"},{"id":74,"value":0.0056165854,"label":"Hypertension","title":"P(A): 0.561%"},{"id":75,"value":0.005681483,"label":"Thrombosis","title":"P(A): 0.568%"},{"id":76,"value":0.0061652645,"label":"Thrombocytopenia","title":"P(A): 0.616%"},{"id":77,"value":0.0068496383,"label":"Cough","title":"P(A): 0.684%"},{"id":78,"value":0.0071092284,"label":"COVID-19","title":"P(A): 0.710%"},{"id":79,"value":0.0071269278,"label":"Hypoaesthesia","title":"P(A): 0.712%"},{"id":80,"value":0.0076048095,"label":"Paraesthesia","title":"P(A): 0.760%"},{"id":81,"value":0.0085546732,"label":"Diarrhoea","title":"P(A): 0.855%"},{"id":82,"value":0.0085959716,"label":"Death","title":"P(A): 0.859%"},{"id":83,"value":0.0088909604,"label":"Cerebrovascular accident","title":"P(A): 0.889%"},{"id":84,"value":0.0101004142,"label":"Chest pain","title":"P(A): 1.010%"},{"id":85,"value":0.0125488206,"label":"Pulmonary embolism","title":"P(A): 1.254%"},{"id":86,"value":0.0131741967,"label":"Pain","title":"P(A): 1.317%"},{"id":87,"value":0.0139293679,"label":"Asthenia","title":"P(A): 1.392%"},{"id":88,"value":0.0140001652,"label":"Vomiting","title":"P(A): 1.400%"},{"id":89,"value":0.0144485481,"label":"Pain in extremity","title":"P(A): 1.444%"},{"id":90,"value":0.0169913509,"label":"Arthralgia","title":"P(A): 1.699%"},{"id":91,"value":0.0179294151,"label":"Malaise","title":"P(A): 1.792%"},{"id":92,"value":0.0200415344,"label":"Dizziness","title":"P(A): 2.004%"},{"id":93,"value":0.0220061594,"label":"Myalgia","title":"P(A): 2.200%"},{"id":94,"value":0.0231566154,"label":"Chills","title":"P(A): 2.315%"},{"id":95,"value":0.0232274127,"label":"Dyspnoea","title":"P(A): 2.322%"},{"id":96,"value":0.0251212404,"label":"Nausea","title":"P(A): 2.512%"},{"id":97,"value":0.0337880093,"label":"Fatigue","title":"P(A): 3.378%"},{"id":98,"value":0.0396287862,"label":"Pyrexia","title":"P(A): 3.962%"},{"id":99,"value":0.0468206115,"label":"Headache","title":"P(A): 4.682%"}]]